{
  "sticker": {},
  "database": {},
  "game": {},
  "others": {},
  "users": {
    "601128344279@s.whatsapp.net": {
      "vip": false,
      "badword": 0,
      "title": "",
      "serialNumber": "baace817a26b17f90da1c5d326dc5286",
      "nick": "MikaAI",
      "premium": false,
      "totalLimit": 0,
      "limit": 30,
      "uang": 10000,
      "lastclaim": 1738921601424,
      "lastrampok": 1738921601424
    },
    "6281371736816@s.whatsapp.net": {
      "vip": false,
      "badword": 0,
      "title": "",
      "serialNumber": "228411ea30491c05894104bda73a94db",
      "nick": ".",
      "premium": false,
      "totalLimit": 0,
      "limit": 30,
      "uang": 10000,
      "lastclaim": 1738921605145,
      "lastrampok": 1738921605145
    },
    "6283143646175@s.whatsapp.net": {
      "vip": false,
      "badword": 0,
      "title": "",
      "serialNumber": "0e4ef2cf93225d881df5af0cb654432f",
      "nick": "ᴸ⅃",
      "premium": false,
      "totalLimit": 0,
      "limit": 30,
      "uang": 10000,
      "lastclaim": 1738921606000,
      "lastrampok": 1738921606000
    },
    "60109500341@s.whatsapp.net": {
      "vip": false,
      "badword": 0,
      "title": "",
      "serialNumber": "b813c9807eaed4cba5c62c72fd957017",
      "nick": "Xinz RESELLER",
      "premium": false,
      "totalLimit": 0,
      "limit": 30,
      "uang": 10000,
      "lastclaim": 1738921990570,
      "lastrampok": 1738921990570
    },
    "62895415930022@s.whatsapp.net": {
      "vip": false,
      "badword": 0,
      "title": "",
      "serialNumber": "d8fb3b8709aa96bb803f309dcf75a8f3",
      "nick": "Shaa.",
      "premium": false,
      "totalLimit": 0,
      "limit": 30,
      "uang": 10000,
      "lastclaim": 1738922089379,
      "lastrampok": 1738922089379
    },
    "60182432916@s.whatsapp.net": {
      "vip": false,
      "badword": 0,
      "title": "",
      "serialNumber": "09fd704152034a2329fccc91b9717d3b",
      "nick": "Fiq",
      "premium": false,
      "totalLimit": 0,
      "limit": 30,
      "uang": 10000,
      "lastclaim": 1738922528729,
      "lastrampok": 1738922528729
    },
    "60182409691@s.whatsapp.net": {
      "vip": false,
      "badword": 0,
      "title": "",
      "serialNumber": "5d76a0388e7daf7376646e2ab1092a2b",
      "nick": "RILL STORE",
      "premium": false,
      "totalLimit": 0,
      "limit": 30,
      "uang": 10000,
      "lastclaim": 1738922608147,
      "lastrampok": 1738922608147
    },
    "60169977283@s.whatsapp.net": {
      "vip": false,
      "badword": 0,
      "title": "",
      "serialNumber": "a762a5c6b454ec651395c05e37a9f5dc",
      "nick": "Just Call Me Dill",
      "premium": false,
      "totalLimit": 0,
      "limit": 30,
      "uang": 10000,
      "lastclaim": 1738922671034,
      "lastrampok": 1738922671034
    },
    "6282335453910@s.whatsapp.net": {
      "vip": false,
      "badword": 0,
      "title": "",
      "serialNumber": "82aa75071f87dcf5a8b2db6fa5656092",
      "nick": "ぼ",
      "premium": false,
      "totalLimit": 0,
      "limit": 30,
      "uang": 10000,
      "lastclaim": 1738922719273,
      "lastrampok": 1738922719273
    },
    "60137134655@s.whatsapp.net": {
      "vip": false,
      "badword": 0,
      "title": "",
      "serialNumber": "db2abcd8c87e7243d8acff3e428abb58",
      "nick": "Kyz Promoter",
      "premium": false,
      "totalLimit": 0,
      "limit": 30,
      "uang": 10000,
      "lastclaim": 1738922830754,
      "lastrampok": 1738922830754
    },
    "60146872696@s.whatsapp.net": {
      "vip": false,
      "badword": 0,
      "title": "",
      "serialNumber": "cb2a7f2cc7c1f90553b6e62bcac00cdd",
      "nick": "EMPTY",
      "premium": false,
      "totalLimit": 0,
      "limit": 30,
      "uang": 10000,
      "lastclaim": 1738923949268,
      "lastrampok": 1738923949268
    },
    "6285269555143@s.whatsapp.net": {
      "vip": false,
      "badword": 0,
      "title": "",
      "serialNumber": "08dbf859f71bb4c5380d87d9c589928f",
      "nick": "LySlow",
      "premium": false,
      "totalLimit": 0,
      "limit": 30,
      "uang": 10000,
      "lastclaim": 1738924299443,
      "lastrampok": 1738924299443
    },
    "6285165526065@s.whatsapp.net": {
      "vip": false,
      "badword": 0,
      "title": "",
      "serialNumber": "694fc992d891a21dae5160b2c0e5bdc3",
      "nick": "sherly",
      "premium": false,
      "totalLimit": 0,
      "limit": 30,
      "uang": 10000,
      "lastclaim": 1738925017145,
      "lastrampok": 1738925017145
    },
    "601161015381@s.whatsapp.net": {
      "vip": false,
      "badword": 0,
      "title": "",
      "serialNumber": "5871ac1068d7eb5b014773c9451e1202",
      "nick": "Aini Frozen",
      "premium": false,
      "totalLimit": 0,
      "limit": 30,
      "uang": 10000,
      "lastclaim": 1738927130042,
      "lastrampok": 1738927130042
    },
    "120363299719848392@newsletter": {
      "vip": false,
      "badword": 0,
      "title": "",
      "serialNumber": "03030f8651367c81f970f19a6561ad7c",
      "premium": false,
      "totalLimit": 0,
      "limit": 30,
      "uang": 10000,
      "lastclaim": 1738927860897,
      "lastrampok": 1738927860897
    },
    "6282118994252@s.whatsapp.net": {
      "vip": false,
      "badword": 0,
      "title": "",
      "serialNumber": "011cec7cae0d25fee0e8c5563b79db31",
      "nick": "RizkyIDK🗿😈",
      "premium": false,
      "totalLimit": 0,
      "limit": 30,
      "uang": 10000,
      "lastclaim": 1738928785604,
      "lastrampok": 1738928785604
    },
    "6283878858005@s.whatsapp.net": {
      "vip": false,
      "badword": 0,
      "title": "",
      "serialNumber": "3fe3eb64ce8912db575a5483cec238b7",
      "nick": "sher",
      "premium": false,
      "totalLimit": 0,
      "limit": 30,
      "uang": 10000,
      "lastclaim": 1738929173884,
      "lastrampok": 1738929173884
    },
    "6285182444284@s.whatsapp.net": {
      "vip": false,
      "badword": 0,
      "title": "",
      "serialNumber": "a690c9137db436da875b0aa05226acd4",
      "nick": "≠TheOnlyWin",
      "premium": false,
      "totalLimit": 0,
      "limit": 30,
      "uang": 10000,
      "lastclaim": 1738930953751,
      "lastrampok": 1738930953751
    },
    "601160805478@s.whatsapp.net": {
      "vip": false,
      "badword": 0,
      "title": "",
      "serialNumber": "dd46f74eb6d4fe37f80dd9dc8a22df83",
      "nick": "~ 𝕹𝖊𝖚𝖊𝖗",
      "premium": false,
      "totalLimit": 0,
      "limit": 30,
      "uang": 10000,
      "lastclaim": 1738931144115,
      "lastrampok": 1738931144115
    },
    "6289525914087@s.whatsapp.net": {
      "vip": false,
      "badword": 0,
      "title": "",
      "serialNumber": "fe4c1811e35483b244e7b0b4c292ec04",
      "nick": "YT:Prima MC🇮🇩",
      "premium": false,
      "totalLimit": 0,
      "limit": 30,
      "uang": 10000,
      "lastclaim": 1738932135957,
      "lastrampok": 1738932135957
    },
    "6282252901036@s.whatsapp.net": {
      "vip": false,
      "badword": 0,
      "title": "",
      "serialNumber": "4d4542840ab3aea6fdeccff9a6cce869",
      "nick": "アダム",
      "premium": false,
      "totalLimit": 0,
      "limit": 30,
      "uang": 10000,
      "lastclaim": 1738933558102,
      "lastrampok": 1738933558102
    },
    "60136614538@s.whatsapp.net": {
      "vip": false,
      "badword": 0,
      "title": "",
      "serialNumber": "c9e972c2e3af91f5a52d53e55c8dafb5",
      "nick": "wanjah",
      "premium": false,
      "totalLimit": 0,
      "limit": 30,
      "uang": 10000,
      "lastclaim": 1738934411955,
      "lastrampok": 1738934411955
    },
    "6289505964707@s.whatsapp.net": {
      "vip": false,
      "badword": 0,
      "title": "",
      "serialNumber": "4479575f8264d82891f0a6e5825e9c90",
      "nick": "~ZAIRAH~",
      "premium": false,
      "totalLimit": 0,
      "limit": 30,
      "uang": 10000,
      "lastclaim": 1738934488252,
      "lastrampok": 1738934488252
    },
    "60163024814@s.whatsapp.net": {
      "vip": false,
      "badword": 0,
      "title": "",
      "serialNumber": "25f620dfe5c6d475000c35e28e3df57a",
      "nick": "𝙁 𝙍 𝙀 𝘿 𝙊",
      "premium": false,
      "totalLimit": 0,
      "limit": 30,
      "uang": 10000,
      "lastclaim": 1738940719115,
      "lastrampok": 1738940719115
    }
  },
  "chats": {
    "601128344279@s.whatsapp.net": {
      "badword": false,
      "antiforeignnum": false,
      "antiviewonce": false,
      "antibot": false,
      "antispam": false,
      "antimedia": false,
      "antiimage": false,
      "antivideo": false,
      "antiaudio": false,
      "antisticker": false,
      "anticontact": false,
      "antilocation": false,
      "antidocument": false,
      "antilink": false,
      "antilinkgc": false,
      "mute": false
    },
    "120363343012435897@g.us": {
      "badword": true,
      "antiforeignnum": false,
      "antiviewonce": false,
      "antibot": false,
      "antispam": false,
      "antimedia": false,
      "antiimage": false,
      "antivideo": false,
      "antiaudio": false,
      "antisticker": false,
      "anticontact": false,
      "antilocation": false,
      "antidocument": false,
      "antilink": false,
      "antilinkgc": false,
      "mute": false
    },
    "60109500341@s.whatsapp.net": {
      "badword": false,
      "antiforeignnum": false,
      "antiviewonce": false,
      "antibot": false,
      "antispam": false,
      "antimedia": false,
      "antiimage": false,
      "antivideo": false,
      "antiaudio": false,
      "antisticker": false,
      "anticontact": false,
      "antilocation": false,
      "antidocument": false,
      "antilink": false,
      "antilinkgc": false,
      "mute": false
    },
    "60182409691@s.whatsapp.net": {
      "badword": false,
      "antiforeignnum": false,
      "antiviewonce": false,
      "antibot": false,
      "antispam": false,
      "antimedia": false,
      "antiimage": false,
      "antivideo": false,
      "antiaudio": false,
      "antisticker": false,
      "anticontact": false,
      "antilocation": false,
      "antidocument": false,
      "antilink": false,
      "antilinkgc": false,
      "mute": false
    },
    "120363378854683193@g.us": {
      "badword": false,
      "antiforeignnum": false,
      "antiviewonce": false,
      "antibot": false,
      "antispam": false,
      "antimedia": false,
      "antiimage": false,
      "antivideo": false,
      "antiaudio": false,
      "antisticker": false,
      "anticontact": false,
      "antilocation": false,
      "antidocument": false,
      "antilink": false,
      "antilinkgc": false,
      "mute": false
    },
    "60109500351@s.whatsapp.net": {
      "badword": false,
      "antiforeignnum": false,
      "antiviewonce": false,
      "antibot": false,
      "antispam": false,
      "antimedia": false,
      "antiimage": false,
      "antivideo": false,
      "antiaudio": false,
      "antisticker": false,
      "anticontact": false,
      "antilocation": false,
      "antidocument": false,
      "antilink": false,
      "antilinkgc": false,
      "mute": false
    },
    "60137134655@s.whatsapp.net": {
      "badword": false,
      "antiforeignnum": false,
      "antiviewonce": false,
      "antibot": false,
      "antispam": false,
      "antimedia": false,
      "antiimage": false,
      "antivideo": false,
      "antiaudio": false,
      "antisticker": false,
      "anticontact": false,
      "antilocation": false,
      "antidocument": false,
      "antilink": false,
      "antilinkgc": false,
      "mute": false
    },
    "120363181678186035@g.us": {
      "badword": false,
      "antiforeignnum": false,
      "antiviewonce": false,
      "antibot": false,
      "antispam": false,
      "antimedia": false,
      "antiimage": false,
      "antivideo": false,
      "antiaudio": false,
      "antisticker": false,
      "anticontact": false,
      "antilocation": false,
      "antidocument": false,
      "antilink": false,
      "antilinkgc": false,
      "mute": false
    },
    "601161015381@s.whatsapp.net": {
      "badword": false,
      "antiforeignnum": false,
      "antiviewonce": false,
      "antibot": false,
      "antispam": false,
      "antimedia": false,
      "antiimage": false,
      "antivideo": false,
      "antiaudio": false,
      "antisticker": false,
      "anticontact": false,
      "antilocation": false,
      "antidocument": false,
      "antilink": false,
      "antilinkgc": false,
      "mute": false
    },
    "120363373717463493@g.us": {
      "badword": false,
      "antiforeignnum": false,
      "antiviewonce": false,
      "antibot": false,
      "antispam": false,
      "antimedia": false,
      "antiimage": false,
      "antivideo": false,
      "antiaudio": false,
      "antisticker": false,
      "anticontact": false,
      "antilocation": false,
      "antidocument": false,
      "antilink": false,
      "antilinkgc": false,
      "mute": false
    },
    "120363299719848392@newsletter": {
      "badword": false,
      "antiforeignnum": false,
      "antiviewonce": false,
      "antibot": false,
      "antispam": false,
      "antimedia": false,
      "antiimage": false,
      "antivideo": false,
      "antiaudio": false,
      "antisticker": false,
      "anticontact": false,
      "antilocation": false,
      "antidocument": false,
      "antilink": false,
      "antilinkgc": false,
      "mute": false
    },
    "6282279687680@s.whatsapp.net": {
      "badword": false,
      "antiforeignnum": false,
      "antiviewonce": false,
      "antibot": false,
      "antispam": false,
      "antimedia": false,
      "antiimage": false,
      "antivideo": false,
      "antiaudio": false,
      "antisticker": false,
      "anticontact": false,
      "antilocation": false,
      "antidocument": false,
      "antilink": false,
      "antilinkgc": false,
      "mute": false
    },
    "120363390219114620@g.us": {
      "badword": false,
      "antiforeignnum": false,
      "antiviewonce": false,
      "antibot": false,
      "antispam": false,
      "antimedia": false,
      "antiimage": false,
      "antivideo": false,
      "antiaudio": false,
      "antisticker": false,
      "anticontact": false,
      "antilocation": false,
      "antidocument": false,
      "antilink": false,
      "antilinkgc": false,
      "mute": false
    },
    "6019500341@s.whatsapp.net": {
      "badword": false,
      "antiforeignnum": false,
      "antiviewonce": false,
      "antibot": false,
      "antispam": false,
      "antimedia": false,
      "antiimage": false,
      "antivideo": false,
      "antiaudio": false,
      "antisticker": false,
      "anticontact": false,
      "antilocation": false,
      "antidocument": false,
      "antilink": false,
      "antilinkgc": false,
      "mute": false
    },
    "120363368076444675@g.us": {
      "badword": false,
      "antiforeignnum": false,
      "antiviewonce": false,
      "antibot": false,
      "antispam": false,
      "antimedia": false,
      "antiimage": false,
      "antivideo": false,
      "antiaudio": false,
      "antisticker": false,
      "anticontact": false,
      "antilocation": false,
      "antidocument": false,
      "antilink": false,
      "antilinkgc": false,
      "mute": false
    },
    "120363378432265215@g.us": {
      "badword": false,
      "antiforeignnum": false,
      "antiviewonce": false,
      "antibot": false,
      "antispam": false,
      "antimedia": false,
      "antiimage": false,
      "antivideo": false,
      "antiaudio": false,
      "antisticker": false,
      "anticontact": false,
      "antilocation": false,
      "antidocument": false,
      "antilink": false,
      "antilinkgc": false,
      "mute": false
    }
  },
  "settings": {
    "601128344279@s.whatsapp.net": {
      "totalhit": 0,
      "totalError": 0,
      "online": false,
      "safesearch": false,
      "autosticker": false,
      "autodownload": false,
      "autobio": true,
      "autopfp": true,
      "autoread": true,
      "autorecordtype": true,
      "autorecord": false,
      "autotype": false,
      "autoblocknum": true,
      "onlygc": false,
      "onlypc": false,
      "watermark": {
        "packname": "Created by",
        "author": "MikaAI!"
      },
      "about": {
        "bot": {
          "nick": "MikaAI",
          "alias": "MikaAI!"
        },
        "owner": {
          "nick": "+60 10-950 0351",
          "alias": "60109500351"
        }
      }
    }
  }
}