{
  "sticker": {},
  "database": {},
  "game": {},
  "others": {},
  "users": {
    "6287844551449@s.whatsapp.net": {
      "vip": false,
      "badword": 0,
      "title": "",
      "serialNumber": "c6d33bc4ce2015d3ee3508c2f229c60f",
      "nick": "+62 878-4455-1449",
      "premium": false,
      "totalLimit": 0,
      "limit": 30,
      "uang": 10000,
      "lastclaim": 1738339000461,
      "lastrampok": 1738339000461
    },
    "6285776658221@s.whatsapp.net": {
      "vip": false,
      "badword": 0,
      "title": "",
      "serialNumber": "a5032c75c3d89a52fedc6306c046ebe4",
      "nick": "Manz",
      "premium": false,
      "totalLimit": 0,
      "limit": 30,
      "uang": 10000,
      "lastclaim": 1738339002236,
      "lastrampok": 1738339002236
    },
    "120363312464118948@newsletter": {
      "vip": false,
      "badword": 0,
      "title": "",
      "serialNumber": "165416caad72122601197f61e0ca01a7",
      "premium": false,
      "totalLimit": 0,
      "limit": 30,
      "uang": 10000,
      "lastclaim": 1738339006130,
      "lastrampok": 1738339006130
    },
    "6283834584187@s.whatsapp.net": {
      "vip": false,
      "badword": 0,
      "title": "",
      "serialNumber": "e65c1ea928b1d1fcbadad54eacd96fde",
      "nick": "kyy",
      "premium": false,
      "totalLimit": 0,
      "limit": 30,
      "uang": 10000,
      "lastclaim": 1738339034064,
      "lastrampok": 1738339034064
    },
    "6281295573231@s.whatsapp.net": {
      "vip": false,
      "badword": 0,
      "title": "",
      "serialNumber": "1b03088041fd99f7d4458f9621ab841c",
      "nick": "kaa",
      "premium": false,
      "totalLimit": 0,
      "limit": 30,
      "uang": 10000,
      "lastclaim": 1738339039392,
      "lastrampok": 1738339039392
    },
    "628888785109@s.whatsapp.net": {
      "vip": false,
      "badword": 0,
      "title": "",
      "serialNumber": "f796431fcc2477bcfedcd3264b684c0b",
      "nick": "langcey★★",
      "premium": false,
      "totalLimit": 0,
      "limit": 30,
      "uang": 10000,
      "lastclaim": 1738339041639,
      "lastrampok": 1738339041639
    },
    "6283895834081@s.whatsapp.net": {
      "vip": false,
      "badword": 0,
      "title": "",
      "serialNumber": "9b71fbff3e94509a1f84505895a4480f",
      "nick": "ditt¥",
      "premium": false,
      "totalLimit": 0,
      "limit": 30,
      "uang": 10000,
      "lastclaim": 1738339046263,
      "lastrampok": 1738339046263
    },
    "6282324262011@s.whatsapp.net": {
      "vip": false,
      "badword": 0,
      "title": "",
      "serialNumber": "440eca75583f0dc27744751d01357a85",
      "nick": "cicelyy",
      "premium": false,
      "totalLimit": 0,
      "limit": 30,
      "uang": 10000,
      "lastclaim": 1738339051531,
      "lastrampok": 1738339051531
    },
    "6285870318888@s.whatsapp.net": {
      "vip": false,
      "badword": 0,
      "title": "",
      "serialNumber": "0a9042dc5fa677c5e395562878c13e7e",
      "nick": "Jacob",
      "premium": false,
      "totalLimit": 0,
      "limit": 30,
      "uang": 10000,
      "lastclaim": 1738339052820,
      "lastrampok": 1738339052820
    },
    "6282146215388@s.whatsapp.net": {
      "vip": false,
      "badword": 0,
      "title": "",
      "serialNumber": "c2f7c927dfd1249f95dc58b8a905635e",
      "nick": "cek maklu",
      "premium": false,
      "totalLimit": 0,
      "limit": 30,
      "uang": 10000,
      "lastclaim": 1738339056135,
      "lastrampok": 1738339056135
    },
    "6283161301908@s.whatsapp.net": {
      "vip": false,
      "badword": 0,
      "title": "",
      "serialNumber": "cf85b3f8d1e7f663a657fbe1e78c03bc",
      "nick": "desz[1908]",
      "premium": false,
      "totalLimit": 0,
      "limit": 30,
      "uang": 10000,
      "lastclaim": 1738339069286,
      "lastrampok": 1738339069286
    },
    "17787173509@s.whatsapp.net": {
      "vip": false,
      "badword": 0,
      "title": "",
      "serialNumber": "1606a0d42232aefc6e8ddbcfb03506df",
      "nick": "penjual kopi",
      "premium": false,
      "totalLimit": 0,
      "limit": 30,
      "uang": 10000,
      "lastclaim": 1738339097149,
      "lastrampok": 1738339097149
    },
    "6283129380840@s.whatsapp.net": {
      "vip": false,
      "badword": 0,
      "title": "",
      "serialNumber": "5082800b16b5ad63c7da05c1790c17d4",
      "nick": "ce🆒",
      "premium": false,
      "totalLimit": 0,
      "limit": 30,
      "uang": 10000,
      "lastclaim": 1738339104933,
      "lastrampok": 1738339104933
    },
    "6282111128440@s.whatsapp.net": {
      "vip": false,
      "badword": 0,
      "title": "",
      "serialNumber": "1ad3d832eb44f79a865e0bdecce1256e",
      "nick": "kunto",
      "premium": false,
      "totalLimit": 0,
      "limit": 30,
      "uang": 10000,
      "lastclaim": 1738339115380,
      "lastrampok": 1738339115380
    },
    "6283852083877@s.whatsapp.net": {
      "vip": false,
      "badword": 0,
      "title": "",
      "serialNumber": "9f39e10b50c3cc1b636bfc1d2e75f7ae",
      "nick": "LEK DULTZY",
      "premium": false,
      "totalLimit": 0,
      "limit": 30,
      "uang": 10000,
      "lastclaim": 1738339117263,
      "lastrampok": 1738339117263
    },
    "6283863611747@s.whatsapp.net": {
      "vip": false,
      "badword": 0,
      "title": "",
      "serialNumber": "38f6f095680d45f3d3c3e2e57c892af7",
      "nick": "dimas",
      "premium": false,
      "totalLimit": 0,
      "limit": 30,
      "uang": 10000,
      "lastclaim": 1738339135637,
      "lastrampok": 1738339135637
    },
    "6288242561146@s.whatsapp.net": {
      "vip": false,
      "badword": 0,
      "title": "",
      "serialNumber": "7bf320380a7503b58e3c53f608eda3fb",
      "nick": ".wnw",
      "premium": false,
      "totalLimit": 0,
      "limit": 30,
      "uang": 10000,
      "lastclaim": 1738339136180,
      "lastrampok": 1738339136180
    },
    "6289527989428@s.whatsapp.net": {
      "vip": false,
      "badword": 0,
      "title": "",
      "serialNumber": "95c29208df39135faecce5df690c5dca",
      "nick": "raa",
      "premium": false,
      "totalLimit": 0,
      "limit": 30,
      "uang": 10000,
      "lastclaim": 1738339180897,
      "lastrampok": 1738339180897
    },
    "6288221433086@s.whatsapp.net": {
      "vip": false,
      "badword": 0,
      "title": "",
      "serialNumber": "c93cea8e757900ca277cf583fa944e3f",
      "nick": "big",
      "premium": false,
      "totalLimit": 0,
      "limit": 30,
      "uang": 10000,
      "lastclaim": 1738339224275,
      "lastrampok": 1738339224275
    },
    "6283152755348@s.whatsapp.net": {
      "vip": false,
      "badword": 0,
      "title": "",
      "serialNumber": "1c01cc1157bde6f1a064fe1de0f9cf7c",
      "nick": "saya orang",
      "premium": false,
      "totalLimit": 0,
      "limit": 30,
      "uang": 10000,
      "lastclaim": 1738339255858,
      "lastrampok": 1738339255858
    },
    "6285766713797@s.whatsapp.net": {
      "vip": false,
      "badword": 0,
      "title": "",
      "serialNumber": "8e5cf765beaaeeabec61d57f348aca77",
      "nick": "Wa Utama F",
      "premium": false,
      "totalLimit": 0,
      "limit": 30,
      "uang": 10000,
      "lastclaim": 1738339257554,
      "lastrampok": 1738339257554
    },
    "6287863829746@s.whatsapp.net": {
      "vip": false,
      "badword": 0,
      "title": "",
      "serialNumber": "3ce34c74bf2dc9e40332442c2ac2570f",
      "nick": "mann",
      "premium": false,
      "totalLimit": 0,
      "limit": 30,
      "uang": 10000,
      "lastclaim": 1738339263732,
      "lastrampok": 1738339263732
    },
    "6285946671335@s.whatsapp.net": {
      "vip": false,
      "badword": 0,
      "title": "",
      "serialNumber": "c235e1eff5bb8db298648522cc89f80f",
      "nick": "ADMIN",
      "premium": false,
      "totalLimit": 0,
      "limit": 30,
      "uang": 10000,
      "lastclaim": 1738339298940,
      "lastrampok": 1738339298940
    },
    "6287844661623@s.whatsapp.net": {
      "vip": false,
      "badword": 0,
      "title": "",
      "serialNumber": "a397ac2f4d5c05506f0b626ecbc4be75",
      "nick": "mela a nya aduh jago bgt",
      "premium": false,
      "totalLimit": 0,
      "limit": 30,
      "uang": 10000,
      "lastclaim": 1738339368869,
      "lastrampok": 1738339368869
    },
    "6283874088244@s.whatsapp.net": {
      "vip": false,
      "badword": 0,
      "title": "",
      "serialNumber": "4ceb658a96be01c03ac413617906c412",
      "nick": "N",
      "premium": false,
      "totalLimit": 0,
      "limit": 30,
      "uang": 10000,
      "lastclaim": 1738339396322,
      "lastrampok": 1738339396322
    },
    "6283824290669@s.whatsapp.net": {
      "vip": false,
      "badword": 0,
      "title": "",
      "serialNumber": "b48078392003650542cac991a0d4e2f6",
      "nick": "Dikqtizeyi",
      "premium": false,
      "totalLimit": 0,
      "limit": 30,
      "uang": 10000,
      "lastclaim": 1738339400524,
      "lastrampok": 1738339400524
    },
    "6285198107016@s.whatsapp.net": {
      "vip": false,
      "badword": 0,
      "title": "",
      "serialNumber": "e6862dc9651cb7a55dba63264715eefa",
      "nick": "myra",
      "premium": false,
      "totalLimit": 0,
      "limit": 30,
      "uang": 10000,
      "lastclaim": 1738339434213,
      "lastrampok": 1738339434213
    },
    "6285147339108@s.whatsapp.net": {
      "vip": false,
      "badword": 0,
      "title": "",
      "serialNumber": "165e6bc6f5da4e65e1d3d62666ff1289",
      "nick": "cathr_",
      "premium": false,
      "totalLimit": 0,
      "limit": 30,
      "uang": 10000,
      "lastclaim": 1738339465855,
      "lastrampok": 1738339465855
    },
    "6282172936844@s.whatsapp.net": {
      "vip": false,
      "badword": 0,
      "title": "",
      "serialNumber": "be28bcc09863c8c1cc714c42f93dbe92",
      "nick": "━⁠☆ﾟ⁠.⁠*elliaaa",
      "premium": false,
      "totalLimit": 0,
      "limit": 30,
      "uang": 10000,
      "lastclaim": 1738339473270,
      "lastrampok": 1738339473270
    },
    "6285232406467@s.whatsapp.net": {
      "vip": false,
      "badword": 0,
      "title": "",
      "serialNumber": "663114d2406ea4d26b21d3663059c3b6",
      "nick": ".",
      "premium": false,
      "totalLimit": 0,
      "limit": 30,
      "uang": 10000,
      "lastclaim": 1738339498838,
      "lastrampok": 1738339498838
    },
    "6282139301910@s.whatsapp.net": {
      "vip": false,
      "badword": 0,
      "title": "",
      "serialNumber": "f85310734380e25aa7b605e1329f248b",
      "nick": "Rizqy",
      "premium": false,
      "totalLimit": 0,
      "limit": 30,
      "uang": 10000,
      "lastclaim": 1738339571586,
      "lastrampok": 1738339571586
    },
    "6283854529216@s.whatsapp.net": {
      "vip": false,
      "badword": 0,
      "title": "",
      "serialNumber": "0e707e448ac9ae55a6fceef8219e31e2",
      "nick": "Okee",
      "premium": false,
      "totalLimit": 0,
      "limit": 30,
      "uang": 10000,
      "lastclaim": 1738339596887,
      "lastrampok": 1738339596887
    },
    "6285781722186@s.whatsapp.net": {
      "vip": false,
      "badword": 0,
      "title": "",
      "serialNumber": "b5ef770dfe6219c83ef7aad7666a6de2",
      "nick": "adt",
      "premium": false,
      "totalLimit": 0,
      "limit": 30,
      "uang": 10000,
      "lastclaim": 1738339597036,
      "lastrampok": 1738339597036
    },
    "6282324034625@s.whatsapp.net": {
      "vip": false,
      "badword": 0,
      "title": "",
      "serialNumber": "dec52c7aee1dee250e8ff33fc318da75",
      "nick": "cama",
      "premium": false,
      "totalLimit": 0,
      "limit": 30,
      "uang": 10000,
      "lastclaim": 1738339663441,
      "lastrampok": 1738339663441
    },
    "6288744074204@s.whatsapp.net": {
      "vip": false,
      "badword": 0,
      "title": "",
      "serialNumber": "3c10ddddba0e9e80a7fb0612bc3048d5",
      "nick": ".",
      "premium": false,
      "totalLimit": 0,
      "limit": 30,
      "uang": 10000,
      "lastclaim": 1738339841050,
      "lastrampok": 1738339841050
    },
    "6283856835305@s.whatsapp.net": {
      "vip": false,
      "badword": 0,
      "title": "",
      "serialNumber": "31fa26a2586d520b0bc0fcb5a5fd8d7b",
      "nick": "cio zeus🇪🇪",
      "premium": false,
      "totalLimit": 0,
      "limit": 30,
      "uang": 10000,
      "lastclaim": 1738339880284,
      "lastrampok": 1738339880284
    },
    "6285710266377@s.whatsapp.net": {
      "vip": false,
      "badword": 0,
      "title": "",
      "serialNumber": "bc2d15a2372b0281cd54923b6497057f",
      "nick": "jamm",
      "premium": false,
      "totalLimit": 0,
      "limit": 30,
      "uang": 10000,
      "lastclaim": 1738339880478,
      "lastrampok": 1738339880478
    },
    "6285174314218@s.whatsapp.net": {
      "vip": false,
      "badword": 0,
      "title": "",
      "serialNumber": "24c9a29eadb97d8d95d1ae8c475c4a2c",
      "nick": "hello",
      "premium": false,
      "totalLimit": 0,
      "limit": 30,
      "uang": 10000,
      "lastclaim": 1738339909646,
      "lastrampok": 1738339909646
    },
    "6287790563424@s.whatsapp.net": {
      "vip": false,
      "badword": 0,
      "title": "",
      "serialNumber": "5923dcfb3aefd96b09a37debe213c361",
      "nick": "𝗥𝗲𝘇𝗼 𝗢𝘁𝘄 𝗽𝗲𝗺𝗲𝘀",
      "premium": false,
      "totalLimit": 0,
      "limit": 30,
      "uang": 10000,
      "lastclaim": 1738339911489,
      "lastrampok": 1738339911489
    },
    "62895396770206@s.whatsapp.net": {
      "vip": false,
      "badword": 0,
      "title": "",
      "serialNumber": "9e2dabd4050b3adf374e1fef257a1968",
      "nick": "ikyikyiky",
      "premium": false,
      "totalLimit": 0,
      "limit": 30,
      "uang": 10000,
      "lastclaim": 1738339931132,
      "lastrampok": 1738339931132
    },
    "6282289473094@s.whatsapp.net": {
      "vip": false,
      "badword": 0,
      "title": "",
      "serialNumber": "eca51b6aed0f037783dc3e5be804bd09",
      "nick": "d",
      "premium": false,
      "totalLimit": 0,
      "limit": 30,
      "uang": 10000,
      "lastclaim": 1738339940486,
      "lastrampok": 1738339940486
    },
    "6282170607427@s.whatsapp.net": {
      "vip": false,
      "badword": 0,
      "title": "",
      "serialNumber": "3fc17db73c57aab621d065ba15f08c95",
      "nick": "🤯",
      "premium": false,
      "totalLimit": 0,
      "limit": 30,
      "uang": 10000,
      "lastclaim": 1738339977140,
      "lastrampok": 1738339977140
    },
    "6283846001334@s.whatsapp.net": {
      "vip": false,
      "badword": 0,
      "title": "",
      "serialNumber": "6a57af9e058c77eaec53e5c89fa87e41",
      "nick": ".",
      "premium": false,
      "totalLimit": 0,
      "limit": 30,
      "uang": 10000,
      "lastclaim": 1738339990600,
      "lastrampok": 1738339990600
    },
    "6282136706100@s.whatsapp.net": {
      "vip": false,
      "badword": 0,
      "title": "",
      "serialNumber": "d52d043f7d3b706a0262c6c2386b6c5d",
      "nick": "zhra",
      "premium": false,
      "totalLimit": 0,
      "limit": 30,
      "uang": 10000,
      "lastclaim": 1738340024054,
      "lastrampok": 1738340024054
    },
    "6282281684427@s.whatsapp.net": {
      "vip": false,
      "badword": 0,
      "title": "",
      "serialNumber": "45f4ec042d97f3f26cbeee693ee004eb",
      "nick": "q.hazril",
      "premium": false,
      "totalLimit": 0,
      "limit": 30,
      "uang": 10000,
      "lastclaim": 1738340033841,
      "lastrampok": 1738340033841
    },
    "6283849035243@s.whatsapp.net": {
      "vip": false,
      "badword": 0,
      "title": "",
      "serialNumber": "c50203a5d92ee0e66fd4bcf10e50059d",
      "nick": "hánz★",
      "premium": false,
      "totalLimit": 0,
      "limit": 30,
      "uang": 10000,
      "lastclaim": 1738340034771,
      "lastrampok": 1738340034771
    },
    "6287860279321@s.whatsapp.net": {
      "vip": false,
      "badword": 0,
      "title": "",
      "serialNumber": "ade98a701d59597af42a09a1ff8c890f",
      "nick": "Boy",
      "premium": false,
      "totalLimit": 0,
      "limit": 30,
      "uang": 10000,
      "lastclaim": 1738340118255,
      "lastrampok": 1738340118255
    },
    "6287817145824@s.whatsapp.net": {
      "vip": false,
      "badword": 0,
      "title": "",
      "serialNumber": "d63db5ae6c9276cb0ca2339f9fe42129",
      "nick": "28azrell🇲🇽🇲🇽🇲🇽",
      "premium": false,
      "totalLimit": 0,
      "limit": 30,
      "uang": 10000,
      "lastclaim": 1738340294094,
      "lastrampok": 1738340294094
    },
    "6289635546914@s.whatsapp.net": {
      "vip": false,
      "badword": 0,
      "title": "",
      "serialNumber": "eab0dd8835b6632ac79a692b3bcc70a7",
      "nick": "zora",
      "premium": false,
      "totalLimit": 0,
      "limit": 30,
      "uang": 10000,
      "lastclaim": 1738340309937,
      "lastrampok": 1738340309937
    },
    "6283870898493@s.whatsapp.net": {
      "vip": false,
      "badword": 0,
      "title": "",
      "serialNumber": "9e9fc7777fdadc8960a97743273b35c2",
      "nick": ".",
      "premium": false,
      "totalLimit": 0,
      "limit": 30,
      "uang": 10000,
      "lastclaim": 1738340338656,
      "lastrampok": 1738340338656
    },
    "120363302583491012@newsletter": {
      "vip": false,
      "badword": 0,
      "title": "",
      "serialNumber": "2417a372c447de4ca434543e4dd735fe",
      "premium": false,
      "totalLimit": 0,
      "limit": 30,
      "uang": 10000,
      "lastclaim": 1738340364748,
      "lastrampok": 1738340364748
    },
    "62895364570209@s.whatsapp.net": {
      "vip": false,
      "badword": 0,
      "title": "",
      "serialNumber": "f6e16b4a9674d015b8fbee34d3e9d526",
      "nick": "Bii",
      "premium": false,
      "totalLimit": 0,
      "limit": 30,
      "uang": 10000,
      "lastclaim": 1738340444640,
      "lastrampok": 1738340444640
    },
    "6288279035402@s.whatsapp.net": {
      "vip": false,
      "badword": 0,
      "title": "",
      "serialNumber": "f1f8efd742ba469757922a96ab8eb79f",
      "nick": "gip",
      "premium": false,
      "totalLimit": 0,
      "limit": 30,
      "uang": 10000,
      "lastclaim": 1738340448489,
      "lastrampok": 1738340448489
    },
    "6288224732474@s.whatsapp.net": {
      "vip": false,
      "badword": 0,
      "title": "",
      "serialNumber": "ff47157ccf12fa86c50be49393226ad8",
      "nick": "Nif",
      "premium": false,
      "totalLimit": 0,
      "limit": 30,
      "uang": 10000,
      "lastclaim": 1738340459511,
      "lastrampok": 1738340459511
    },
    "6285232393802@s.whatsapp.net": {
      "vip": false,
      "badword": 0,
      "title": "",
      "serialNumber": "ecf5b87b4860aa6e64dcc1aeeb75acdc",
      "nick": "Astur Lion",
      "premium": false,
      "totalLimit": 0,
      "limit": 30,
      "uang": 10000,
      "lastclaim": 1738340479269,
      "lastrampok": 1738340479269
    },
    "120363344401749353@newsletter": {
      "vip": false,
      "badword": 0,
      "title": "",
      "serialNumber": "b9e92cfcc2c770b33c9b05ce42c7d6d7",
      "premium": false,
      "totalLimit": 0,
      "limit": 30,
      "uang": 10000,
      "lastclaim": 1738340520790,
      "lastrampok": 1738340520790
    },
    "6285624079619@s.whatsapp.net": {
      "vip": false,
      "badword": 0,
      "title": "",
      "serialNumber": "9abf278182a981131e79de4dd9969368",
      "nick": "VAN STR",
      "premium": false,
      "totalLimit": 0,
      "limit": 30,
      "uang": 10000,
      "lastclaim": 1738340521555,
      "lastrampok": 1738340521555
    },
    "628816384149@s.whatsapp.net": {
      "vip": false,
      "badword": 0,
      "title": "",
      "serialNumber": "ef03c4bf3f700839f525709f9bba0778",
      "nick": "P",
      "premium": false,
      "totalLimit": 0,
      "limit": 30,
      "uang": 10000,
      "lastclaim": 1738340586946,
      "lastrampok": 1738340586946
    },
    "6288227357019@s.whatsapp.net": {
      "vip": false,
      "badword": 0,
      "title": "",
      "serialNumber": "12a9a72856c253e43f355076a34fd947",
      "nick": "Royan_",
      "premium": false,
      "totalLimit": 0,
      "limit": 30,
      "uang": 10000,
      "lastclaim": 1738340644021,
      "lastrampok": 1738340644021
    },
    "6285134986948@s.whatsapp.net": {
      "vip": false,
      "badword": 0,
      "title": "",
      "serialNumber": "e9f18351f3714b5dd120b049fb402f6f",
      "nick": "alicherylv:c",
      "premium": false,
      "totalLimit": 0,
      "limit": 30,
      "uang": 10000,
      "lastclaim": 1738340660892,
      "lastrampok": 1738340660892
    },
    "6283133984733@s.whatsapp.net": {
      "vip": false,
      "badword": 0,
      "title": "",
      "serialNumber": "99a77e279d0ebff0d96bcb1b2c47f070",
      "nick": "@xpqx",
      "premium": false,
      "totalLimit": 0,
      "limit": 30,
      "uang": 10000,
      "lastclaim": 1738340663191,
      "lastrampok": 1738340663191
    },
    "6285262638013@s.whatsapp.net": {
      "vip": false,
      "badword": 0,
      "title": "",
      "serialNumber": "d33da78ca9e24ab9e14bf83f0bd015fc",
      "nick": "dyy",
      "premium": false,
      "totalLimit": 0,
      "limit": 30,
      "uang": 10000,
      "lastclaim": 1738340739730,
      "lastrampok": 1738340739730
    },
    "6285862751671@s.whatsapp.net": {
      "vip": false,
      "badword": 0,
      "title": "",
      "serialNumber": "bda7e51debaaa3bd7f8bf302f2a15ca7",
      "nick": ".",
      "premium": false,
      "totalLimit": 0,
      "limit": 30,
      "uang": 10000,
      "lastclaim": 1738340786028,
      "lastrampok": 1738340786028
    },
    "6285387660956@s.whatsapp.net": {
      "vip": false,
      "badword": 0,
      "title": "",
      "serialNumber": "592ab40f2e912e77d3c8f88f478849e0",
      "nick": "aldi",
      "premium": false,
      "totalLimit": 0,
      "limit": 30,
      "uang": 10000,
      "lastclaim": 1738340806650,
      "lastrampok": 1738340806650
    },
    "6282194923601@s.whatsapp.net": {
      "vip": false,
      "badword": 0,
      "title": "",
      "serialNumber": "d7688ba42903e2a12cf9de7746e904b4",
      "nick": "yfndri_",
      "premium": false,
      "totalLimit": 0,
      "limit": 30,
      "uang": 10000,
      "lastclaim": 1738340810265,
      "lastrampok": 1738340810265
    },
    "6289523754197@s.whatsapp.net": {
      "vip": false,
      "badword": 0,
      "title": "",
      "serialNumber": "0ea2c507d874bb493dce5c0a1203b958",
      "nick": "kenz",
      "premium": false,
      "totalLimit": 0,
      "limit": 30,
      "uang": 10000,
      "lastclaim": 1738340825747,
      "lastrampok": 1738340825747
    },
    "6281242227672@s.whatsapp.net": {
      "vip": false,
      "badword": 0,
      "title": "",
      "serialNumber": "ff33e7d57e37b3cf1110671af8331759",
      "nick": "yy",
      "premium": false,
      "totalLimit": 0,
      "limit": 30,
      "uang": 10000,
      "lastclaim": 1738340834355,
      "lastrampok": 1738340834355
    },
    "6281617905110@s.whatsapp.net": {
      "vip": false,
      "badword": 0,
      "title": "",
      "serialNumber": "36493a48bfbe5e1907f8fd8978c580b7",
      "nick": "langggg",
      "premium": false,
      "totalLimit": 0,
      "limit": 30,
      "uang": 10000,
      "lastclaim": 1738340847661,
      "lastrampok": 1738340847661
    },
    "6282310706698@s.whatsapp.net": {
      "vip": false,
      "badword": 0,
      "title": "",
      "serialNumber": "a9a365860039ef4ab23aa80b3e090c4c",
      "nick": "icikiwir",
      "premium": false,
      "totalLimit": 0,
      "limit": 30,
      "uang": 10000,
      "lastclaim": 1738340857878,
      "lastrampok": 1738340857878
    },
    "6282154756282@s.whatsapp.net": {
      "vip": false,
      "badword": 0,
      "title": "",
      "serialNumber": "61a701ba25e1bcf9647ddd5501b8b6a6",
      "nick": "A TR",
      "premium": false,
      "totalLimit": 0,
      "limit": 30,
      "uang": 10000,
      "lastclaim": 1738340973555,
      "lastrampok": 1738340973555
    },
    "6282123275511@s.whatsapp.net": {
      "vip": false,
      "badword": 0,
      "title": "",
      "serialNumber": "c6650a0f0beee3596921c2b5b0246f03",
      "nick": "KIYASH",
      "premium": false,
      "totalLimit": 0,
      "limit": 30,
      "uang": 10000,
      "lastclaim": 1738341009147,
      "lastrampok": 1738341009147
    },
    "62895415223739@s.whatsapp.net": {
      "vip": false,
      "badword": 0,
      "title": "",
      "serialNumber": "b15c71fa7bb12491bd7a011b0abca6f4",
      "nick": "@niarapip",
      "premium": false,
      "totalLimit": 0,
      "limit": 30,
      "uang": 10000,
      "lastclaim": 1738341070640,
      "lastrampok": 1738341070640
    },
    "6283142907119@s.whatsapp.net": {
      "vip": false,
      "badword": 0,
      "title": "",
      "serialNumber": "39583b6a5fef3d8d8291900b6a98e3b1",
      "nick": ".",
      "premium": false,
      "totalLimit": 0,
      "limit": 30,
      "uang": 10000,
      "lastclaim": 1738341173279,
      "lastrampok": 1738341173279
    },
    "6281248590570@s.whatsapp.net": {
      "vip": false,
      "badword": 0,
      "title": "",
      "serialNumber": "07b28788fa20cdc22d1e53d7ff1666cd",
      "nick": "Tuan Kentzyy.",
      "premium": false,
      "totalLimit": 0,
      "limit": 30,
      "uang": 10000,
      "lastclaim": 1738341218229,
      "lastrampok": 1738341218229
    },
    "6289531068458@s.whatsapp.net": {
      "vip": false,
      "badword": 0,
      "title": "",
      "serialNumber": "68f1dd65ab038285c11df6bdc25f9122",
      "nick": "jeko",
      "premium": false,
      "totalLimit": 0,
      "limit": 30,
      "uang": 10000,
      "lastclaim": 1738341228020,
      "lastrampok": 1738341228020
    },
    "628567101398@s.whatsapp.net": {
      "vip": false,
      "badword": 0,
      "title": "",
      "serialNumber": "8bffb210e088a75be24700491c0fbeb7",
      "nick": "MINZZ [398]",
      "premium": false,
      "totalLimit": 0,
      "limit": 30,
      "uang": 10000,
      "lastclaim": 1738341243156,
      "lastrampok": 1738341243156
    },
    "6281260271496@s.whatsapp.net": {
      "vip": false,
      "badword": 0,
      "title": "",
      "serialNumber": "71643076cf7deb4acc4905793337238d",
      "nick": "c",
      "premium": false,
      "totalLimit": 0,
      "limit": 30,
      "uang": 10000,
      "lastclaim": 1738341267948,
      "lastrampok": 1738341267948
    },
    "6282286418072@s.whatsapp.net": {
      "vip": false,
      "badword": 0,
      "title": "",
      "serialNumber": "2c1995b107c4669b4f6516a5df2a0d52",
      "nick": "apiww`",
      "premium": false,
      "totalLimit": 0,
      "limit": 30,
      "uang": 10000,
      "lastclaim": 1738341317042,
      "lastrampok": 1738341317042
    },
    "6282188770250@s.whatsapp.net": {
      "vip": false,
      "badword": 0,
      "title": "",
      "serialNumber": "5ec0d3e75928d73d718e0882921ff042",
      "nick": "Farhan",
      "premium": false,
      "totalLimit": 0,
      "limit": 30,
      "uang": 10000,
      "lastclaim": 1738341330802,
      "lastrampok": 1738341330802
    },
    "6289656228350@s.whatsapp.net": {
      "vip": false,
      "badword": 0,
      "title": "",
      "serialNumber": "c49ec2a6549d1d6f6227dfdcd8668975",
      "nick": "anonymous",
      "premium": false,
      "totalLimit": 0,
      "limit": 30,
      "uang": 10000,
      "lastclaim": 1738341339753,
      "lastrampok": 1738341339753
    },
    "6281217937383@s.whatsapp.net": {
      "vip": false,
      "badword": 0,
      "title": "",
      "serialNumber": "7d0d32b5d77329c6a61db4287afaf39e",
      "nick": "RexxyXD",
      "premium": false,
      "totalLimit": 0,
      "limit": 30,
      "uang": 10000,
      "lastclaim": 1738341340460,
      "lastrampok": 1738341340460
    },
    "6283121130606@s.whatsapp.net": {
      "vip": false,
      "badword": 0,
      "title": "",
      "serialNumber": "a931b33456290e6ab00df85bcf8e4018",
      "nick": "jepp www",
      "premium": false,
      "totalLimit": 0,
      "limit": 30,
      "uang": 10000,
      "lastclaim": 1738341373676,
      "lastrampok": 1738341373676
    },
    "6285770820726@s.whatsapp.net": {
      "vip": false,
      "badword": 0,
      "title": "",
      "serialNumber": "c4f650729d730e363246332b27aa5bca",
      "nick": "hann",
      "premium": false,
      "totalLimit": 0,
      "limit": 30,
      "uang": 10000,
      "lastclaim": 1738341464650,
      "lastrampok": 1738341464650
    },
    "6282240218057@s.whatsapp.net": {
      "vip": false,
      "badword": 0,
      "title": "",
      "serialNumber": "b25f5f6e4f58983950d4d93c23a12a0e",
      "nick": "𝗬𝗮𝗻𝗻 𝗼𝘄𝗻 𝗿𝗲𝘆𝘆 𝗸𝘄 ꨄඩා",
      "premium": false,
      "totalLimit": 0,
      "limit": 30,
      "uang": 10000,
      "lastclaim": 1738341470926,
      "lastrampok": 1738341470926
    },
    "6289530636352@s.whatsapp.net": {
      "vip": false,
      "badword": 0,
      "title": "",
      "serialNumber": "033fdcbff362af0b3a614c4c03c41778",
      "nick": "ler",
      "premium": false,
      "totalLimit": 0,
      "limit": 30,
      "uang": 10000,
      "lastclaim": 1738341475829,
      "lastrampok": 1738341475829
    },
    "6289651772030@s.whatsapp.net": {
      "vip": false,
      "badword": 0,
      "title": "",
      "serialNumber": "296c37ae2191ea5c0c56dac48c3dbcd0",
      "nick": "davin ★",
      "premium": false,
      "totalLimit": 0,
      "limit": 30,
      "uang": 10000,
      "lastclaim": 1738341477042,
      "lastrampok": 1738341477042
    },
    "6283878041361@s.whatsapp.net": {
      "vip": false,
      "badword": 0,
      "title": "",
      "serialNumber": "4f24e87fe6e8d2327100ad4240c1ac8a",
      "nick": "ksha",
      "premium": false,
      "totalLimit": 0,
      "limit": 30,
      "uang": 10000,
      "lastclaim": 1738341546536,
      "lastrampok": 1738341546536
    },
    "6283186982344@s.whatsapp.net": {
      "vip": false,
      "badword": 0,
      "title": "",
      "serialNumber": "f2dc7e3cd02fd820af2b24c5e990a588",
      "nick": "rifki",
      "premium": false,
      "totalLimit": 0,
      "limit": 30,
      "uang": 10000,
      "lastclaim": 1738341548939,
      "lastrampok": 1738341548939
    },
    "6283150120431@s.whatsapp.net": {
      "vip": false,
      "badword": 0,
      "title": "",
      "serialNumber": "e1d40008345152d6e08bc4d0d708a70d",
      "nick": "komengz!!",
      "premium": false,
      "totalLimit": 0,
      "limit": 30,
      "uang": 10000,
      "lastclaim": 1738341556011,
      "lastrampok": 1738341556011
    },
    "62882022591457@s.whatsapp.net": {
      "vip": false,
      "badword": 0,
      "title": "",
      "serialNumber": "a55b79c3dcdc75cc4b0ba60eb1b2667f",
      "nick": "userrr999fhmii",
      "premium": false,
      "totalLimit": 0,
      "limit": 30,
      "uang": 10000,
      "lastclaim": 1738341593451,
      "lastrampok": 1738341593452
    },
    "6288245563507@s.whatsapp.net": {
      "vip": false,
      "badword": 0,
      "title": "",
      "serialNumber": "25e9328f32885c512cd2b619b66bdcd7",
      "nick": "rahmat",
      "premium": false,
      "totalLimit": 0,
      "limit": 30,
      "uang": 10000,
      "lastclaim": 1738341597125,
      "lastrampok": 1738341597125
    },
    "6285183706254@s.whatsapp.net": {
      "vip": false,
      "badword": 0,
      "title": "",
      "serialNumber": "1a21866b2380b68ed7e4a0cf6402066e",
      "nick": "roky",
      "premium": false,
      "totalLimit": 0,
      "limit": 30,
      "uang": 10000,
      "lastclaim": 1738341598996,
      "lastrampok": 1738341598996
    },
    "6283139578685@s.whatsapp.net": {
      "vip": false,
      "badword": 0,
      "title": "",
      "serialNumber": "d1f34570d409755379a1f1345fe381cf",
      "nick": "shiro19%",
      "premium": false,
      "totalLimit": 0,
      "limit": 30,
      "uang": 10000,
      "lastclaim": 1738341641713,
      "lastrampok": 1738341641713
    },
    "6289691166386@s.whatsapp.net": {
      "vip": false,
      "badword": 0,
      "title": "",
      "serialNumber": "53a753c86749344bbe3e14b410a4b3f3",
      "nick": "hohoho",
      "premium": false,
      "totalLimit": 0,
      "limit": 30,
      "uang": 10000,
      "lastclaim": 1738341721759,
      "lastrampok": 1738341721759
    },
    "6285769561393@s.whatsapp.net": {
      "vip": false,
      "badword": 0,
      "title": "",
      "serialNumber": "c3c5bca374fba1850ac7191862a3fe11",
      "nick": "licㅤ",
      "premium": false,
      "totalLimit": 0,
      "limit": 30,
      "uang": 10000,
      "lastclaim": 1738341753916,
      "lastrampok": 1738341753916
    },
    "6287840006942@s.whatsapp.net": {
      "vip": false,
      "badword": 0,
      "title": "",
      "serialNumber": "09a81be84f6a54959bf0d09b5a615fbc",
      "nick": "dor dor dor",
      "premium": false,
      "totalLimit": 0,
      "limit": 30,
      "uang": 10000,
      "lastclaim": 1738341791273,
      "lastrampok": 1738341791273
    },
    "6288299489514@s.whatsapp.net": {
      "vip": false,
      "badword": 0,
      "title": "",
      "serialNumber": "5d0c22774c3ee27af19d268916184a42",
      "nick": "f",
      "premium": false,
      "totalLimit": 0,
      "limit": 30,
      "uang": 10000,
      "lastclaim": 1738341806317,
      "lastrampok": 1738341806317
    },
    "6281210219310@s.whatsapp.net": {
      "vip": false,
      "badword": 0,
      "title": "",
      "serialNumber": "f1a6720aaaeab5e3122c7e1f3c4dc4bd",
      "nick": "Wis",
      "premium": false,
      "totalLimit": 0,
      "limit": 30,
      "uang": 10000,
      "lastclaim": 1738341849840,
      "lastrampok": 1738341849840
    },
    "6289512961794@s.whatsapp.net": {
      "vip": false,
      "badword": 0,
      "title": "",
      "serialNumber": "453a7a689fcb94e4645a77a4cef704a1",
      "nick": "DAPPAXX [1794]",
      "premium": false,
      "totalLimit": 0,
      "limit": 30,
      "uang": 10000,
      "lastclaim": 1738341878844,
      "lastrampok": 1738341878844
    },
    "6283846246470@s.whatsapp.net": {
      "vip": false,
      "badword": 0,
      "title": "",
      "serialNumber": "be4f28eec040391bc917ae161896fe41",
      "nick": "Yunn[6470]",
      "premium": false,
      "totalLimit": 0,
      "limit": 30,
      "uang": 10000,
      "lastclaim": 1738341906487,
      "lastrampok": 1738341906487
    },
    "6285816308659@s.whatsapp.net": {
      "vip": false,
      "badword": 0,
      "title": "",
      "serialNumber": "51f7d84b30c0a478609e1e8494e38f04",
      "nick": "mengzz",
      "premium": false,
      "totalLimit": 0,
      "limit": 30,
      "uang": 10000,
      "lastclaim": 1738341941978,
      "lastrampok": 1738341941978
    },
    "6281933582607@s.whatsapp.net": {
      "vip": false,
      "badword": 0,
      "title": "",
      "serialNumber": "d1372207a9a1764c4d96df76ab61ae05",
      "nick": "raka",
      "premium": false,
      "totalLimit": 0,
      "limit": 30,
      "uang": 10000,
      "lastclaim": 1738341970745,
      "lastrampok": 1738341970745
    },
    "6285849120930@s.whatsapp.net": {
      "vip": false,
      "badword": 0,
      "title": "",
      "serialNumber": "2b9ad525707603f325a7b627fa3bfd8c",
      "nick": "jse wnita gmes",
      "premium": false,
      "totalLimit": 0,
      "limit": 30,
      "uang": 10000,
      "lastclaim": 1738341971331,
      "lastrampok": 1738341971331
    },
    "6285762607494@s.whatsapp.net": {
      "vip": false,
      "badword": 0,
      "title": "",
      "serialNumber": "b3b12bc320ea647a33db2ebb3712214d",
      "nick": "saddiq [7494]",
      "premium": false,
      "totalLimit": 0,
      "limit": 30,
      "uang": 10000,
      "lastclaim": 1738341986774,
      "lastrampok": 1738341986774
    },
    "6285737498293@s.whatsapp.net": {
      "vip": false,
      "badword": 0,
      "title": "",
      "serialNumber": "a045537037f82a695228a9184943ae85",
      "nick": "velin",
      "premium": false,
      "totalLimit": 0,
      "limit": 30,
      "uang": 10000,
      "lastclaim": 1738342020150,
      "lastrampok": 1738342020150
    },
    "6285198412928@s.whatsapp.net": {
      "vip": false,
      "badword": 0,
      "title": "",
      "serialNumber": "7866c7605e79500c3923f7d49dcc3993",
      "nick": "kyy ˢᵃᵈᶦˢᵗᶦᶜ",
      "premium": false,
      "totalLimit": 0,
      "limit": 30,
      "uang": 10000,
      "lastclaim": 1738342022097,
      "lastrampok": 1738342022097
    },
    "6289529838834@s.whatsapp.net": {
      "vip": false,
      "badword": 0,
      "title": "",
      "serialNumber": "5491277505987b8c9d85e935bedeb1e2",
      "nick": "pacee",
      "premium": false,
      "totalLimit": 0,
      "limit": 30,
      "uang": 10000,
      "lastclaim": 1738342052541,
      "lastrampok": 1738342052541
    },
    "6282147868741@s.whatsapp.net": {
      "vip": false,
      "badword": 0,
      "title": "",
      "serialNumber": "40b4abc1a3f4c30570570aeb156bc573",
      "nick": "BEYZ STORE ( OWNER MARVIL)",
      "premium": false,
      "totalLimit": 0,
      "limit": 30,
      "uang": 10000,
      "lastclaim": 1738342076564,
      "lastrampok": 1738342076564
    },
    "6282325558294@s.whatsapp.net": {
      "vip": false,
      "badword": 0,
      "title": "",
      "serialNumber": "d3fedc77ee9fadfd251d443ab0d7b50a",
      "nick": "pp",
      "premium": false,
      "totalLimit": 0,
      "limit": 30,
      "uang": 10000,
      "lastclaim": 1738342098643,
      "lastrampok": 1738342098643
    },
    "6285751481930@s.whatsapp.net": {
      "vip": false,
      "badword": 0,
      "title": "",
      "serialNumber": "c219cbe0e524b47fca95978f5c37cab2",
      "nick": "MADZ STORE",
      "premium": false,
      "totalLimit": 0,
      "limit": 30,
      "uang": 10000,
      "lastclaim": 1738342112151,
      "lastrampok": 1738342112151
    },
    "6285772768522@s.whatsapp.net": {
      "vip": false,
      "badword": 0,
      "title": "",
      "serialNumber": "b170130985208b7948416e43cd950437",
      "nick": "celovvip",
      "premium": false,
      "totalLimit": 0,
      "limit": 30,
      "uang": 10000,
      "lastclaim": 1738342119846,
      "lastrampok": 1738342119846
    },
    "6289646395700@s.whatsapp.net": {
      "vip": false,
      "badword": 0,
      "title": "",
      "serialNumber": "92817a1c9db4b9fe40567effbe8cde22",
      "nick": "Jpm",
      "premium": false,
      "totalLimit": 0,
      "limit": 30,
      "uang": 10000,
      "lastclaim": 1738342374637,
      "lastrampok": 1738342374637
    },
    "628973167550@s.whatsapp.net": {
      "vip": false,
      "badword": 0,
      "title": "",
      "serialNumber": "d0e2809c9be5a66cd7ca056e0613f67c",
      "nick": "@ridparid",
      "premium": false,
      "totalLimit": 0,
      "limit": 30,
      "uang": 10000,
      "lastclaim": 1738342500851,
      "lastrampok": 1738342500851
    },
    "6285608447883@s.whatsapp.net": {
      "vip": false,
      "badword": 0,
      "title": "",
      "serialNumber": "66030bb41f6ca16c87ab12a1022fc663",
      "nick": "tyerxzz",
      "premium": false,
      "totalLimit": 0,
      "limit": 30,
      "uang": 10000,
      "lastclaim": 1738342550469,
      "lastrampok": 1738342550469
    },
    "62882021409733@s.whatsapp.net": {
      "vip": false,
      "badword": 0,
      "title": "",
      "serialNumber": "4844de3d43e516c49d560e64b4b4b1d6",
      "nick": "p",
      "premium": false,
      "totalLimit": 0,
      "limit": 30,
      "uang": 10000,
      "lastclaim": 1738342570253,
      "lastrampok": 1738342570253
    },
    "6285794062263@s.whatsapp.net": {
      "vip": false,
      "badword": 0,
      "title": "",
      "serialNumber": "4e47271fcc030199007c2cec936c486d",
      "nick": "pria_misterius",
      "premium": false,
      "totalLimit": 0,
      "limit": 30,
      "uang": 10000,
      "lastclaim": 1738342582617,
      "lastrampok": 1738342582617
    },
    "6283831974947@s.whatsapp.net": {
      "vip": false,
      "badword": 0,
      "title": "",
      "serialNumber": "512b8aba693f82447690dca943c42291",
      "nick": "LUXXY",
      "premium": false,
      "totalLimit": 0,
      "limit": 30,
      "uang": 10000,
      "lastclaim": 1738342611762,
      "lastrampok": 1738342611762
    },
    "62858647290531@s.whatsapp.net": {
      "vip": false,
      "badword": 0,
      "title": "",
      "serialNumber": "05274d191f09bc76faa1f43a045a87e3",
      "nick": "RUOKK",
      "premium": false,
      "totalLimit": 0,
      "limit": 30,
      "uang": 10000,
      "lastclaim": 1738342620883,
      "lastrampok": 1738342620883
    },
    "6288293077483@s.whatsapp.net": {
      "vip": false,
      "badword": 0,
      "title": "",
      "serialNumber": "14afa9326b62562c29a52ea06a838005",
      "nick": "rafi",
      "premium": false,
      "totalLimit": 0,
      "limit": 30,
      "uang": 10000,
      "lastclaim": 1738342711765,
      "lastrampok": 1738342711765
    },
    "6289669722190@s.whatsapp.net": {
      "vip": false,
      "badword": 0,
      "title": "",
      "serialNumber": "c2d27a1010f3ab126055ac29974728b5",
      "nick": "hilih",
      "premium": false,
      "totalLimit": 0,
      "limit": 30,
      "uang": 10000,
      "lastclaim": 1738342749649,
      "lastrampok": 1738342749649
    },
    "62881011602915@s.whatsapp.net": {
      "vip": false,
      "badword": 0,
      "title": "",
      "serialNumber": "d9836989beb25efd7225a5b3685cc3b7",
      "nick": "barzzzz",
      "premium": false,
      "totalLimit": 0,
      "limit": 100,
      "uang": 10000,
      "lastclaim": 1738342818966,
      "lastrampok": 1738342818966
    },
    "6285600562479@s.whatsapp.net": {
      "vip": false,
      "badword": 0,
      "title": "",
      "serialNumber": "89a72c7d478bc49d954dcdb910ad4c93",
      "nick": "zaa",
      "premium": false,
      "totalLimit": 0,
      "limit": 100,
      "uang": 10000,
      "lastclaim": 1738342852825,
      "lastrampok": 1738342852825
    },
    "6285348283331@s.whatsapp.net": {
      "vip": false,
      "badword": 0,
      "title": "",
      "serialNumber": "235b0ab9303913fc1841f4e0eda21ee9",
      "nick": "ya",
      "premium": false,
      "totalLimit": 0,
      "limit": 100,
      "uang": 10000,
      "lastclaim": 1738342900416,
      "lastrampok": 1738342900416
    },
    "120363159552753674@newsletter": {
      "vip": false,
      "badword": 0,
      "title": "",
      "serialNumber": "d693cfa438611077cfdc9b2da1d735fe",
      "premium": false,
      "totalLimit": 0,
      "limit": 100,
      "uang": 10000,
      "lastclaim": 1738342907052,
      "lastrampok": 1738342907052
    },
    "6282348998064@s.whatsapp.net": {
      "vip": false,
      "badword": 0,
      "title": "",
      "serialNumber": "87f47e3e1725c3594ba4db49e24dffc3",
      "nick": "YAZZX",
      "premium": false,
      "totalLimit": 0,
      "limit": 100,
      "uang": 10000,
      "lastclaim": 1738342963536,
      "lastrampok": 1738342963536
    },
    "62882009521631@s.whatsapp.net": {
      "vip": false,
      "badword": 0,
      "title": "",
      "serialNumber": "f41787ade1d42c629a3185598ff7cd49",
      "nick": "HHHHHHH",
      "premium": false,
      "totalLimit": 0,
      "limit": 100,
      "uang": 10000,
      "lastclaim": 1738343093643,
      "lastrampok": 1738343093643
    },
    "6283170778179@s.whatsapp.net": {
      "vip": false,
      "badword": 0,
      "title": "",
      "serialNumber": "ee730f5b6fde28d6a87530ffedd5741e",
      "nick": "PITRI STORE",
      "premium": false,
      "totalLimit": 0,
      "limit": 100,
      "uang": 10000,
      "lastclaim": 1738343403233,
      "lastrampok": 1738343403233
    },
    "6287732592211@s.whatsapp.net": {
      "vip": false,
      "badword": 0,
      "title": "",
      "serialNumber": "3e17485936bf1be61778a9c689a18ce2",
      "nick": "Eposs rizz💫",
      "premium": false,
      "totalLimit": 0,
      "limit": 100,
      "uang": 10000,
      "lastclaim": 1738343476186,
      "lastrampok": 1738343476186
    },
    "62895325748513@s.whatsapp.net": {
      "vip": false,
      "badword": 0,
      "title": "",
      "serialNumber": "b31fdb40e901b58d3d167ae56d8ac003",
      "nick": ".",
      "premium": false,
      "totalLimit": 0,
      "limit": 100,
      "uang": 10000,
      "lastclaim": 1738343509749,
      "lastrampok": 1738343509749
    },
    "6289515569752@s.whatsapp.net": {
      "vip": false,
      "badword": 0,
      "title": "",
      "serialNumber": "388b2198d6c210284ebfae1e55d532ed",
      "nick": "ABYY",
      "premium": false,
      "totalLimit": 0,
      "limit": 100,
      "uang": 10000,
      "lastclaim": 1738343586567,
      "lastrampok": 1738343586567
    },
    "6287769683097@s.whatsapp.net": {
      "vip": false,
      "badword": 0,
      "title": "",
      "serialNumber": "3ddd886be61211885aa857885841bec2",
      "nick": "Farhan\"__",
      "premium": false,
      "totalLimit": 0,
      "limit": 100,
      "uang": 10000,
      "lastclaim": 1738343767648,
      "lastrampok": 1738343767648
    },
    "6288272172764@s.whatsapp.net": {
      "vip": false,
      "badword": 0,
      "title": "",
      "serialNumber": "9a819788b9536822106b3539d301fbf3",
      "nick": "ราชินีciya",
      "premium": false,
      "totalLimit": 0,
      "limit": 100,
      "uang": 10000,
      "lastclaim": 1738343795141,
      "lastrampok": 1738343795141
    },
    "6281289858895@s.whatsapp.net": {
      "vip": false,
      "badword": 0,
      "title": "",
      "serialNumber": "73dca5592da9ab16aea46cef07a90cc5",
      "nick": "Kyy",
      "premium": false,
      "totalLimit": 0,
      "limit": 100,
      "uang": 10000,
      "lastclaim": 1738343906705,
      "lastrampok": 1738343906705
    },
    "6283863815956@s.whatsapp.net": {
      "vip": false,
      "badword": 0,
      "title": "",
      "serialNumber": "1588068a72f757a16ee5a8b07fedb16b",
      "nick": "-ta new perform",
      "premium": false,
      "totalLimit": 0,
      "limit": 100,
      "uang": 10000,
      "lastclaim": 1738343922803,
      "lastrampok": 1738343922803
    },
    "6285790473714@s.whatsapp.net": {
      "vip": false,
      "badword": 0,
      "title": "",
      "serialNumber": "8a79be25672f958e6b06e29b99bc34b2",
      "nick": "Relz",
      "premium": false,
      "totalLimit": 0,
      "limit": 100,
      "uang": 10000,
      "lastclaim": 1738343963971,
      "lastrampok": 1738343963971
    },
    "6285832946046@s.whatsapp.net": {
      "vip": false,
      "badword": 0,
      "title": "",
      "serialNumber": "cb7505dd5787f09cf11306907ba23c6f",
      "nick": "bill's",
      "premium": false,
      "totalLimit": 0,
      "limit": 100,
      "uang": 10000,
      "lastclaim": 1738343985235,
      "lastrampok": 1738343985235
    },
    "6281324493115@s.whatsapp.net": {
      "vip": false,
      "badword": 0,
      "title": "",
      "serialNumber": "80717b122f311e4f3f187ac36b6f4d21",
      "nick": "𝟕𝟕𝟕 gracelysilvá",
      "premium": false,
      "totalLimit": 0,
      "limit": 100,
      "uang": 10000,
      "lastclaim": 1738344017929,
      "lastrampok": 1738344017929
    },
    "6281227723883@s.whatsapp.net": {
      "vip": false,
      "badword": 0,
      "title": "",
      "serialNumber": "68405d70e01abe0ee152adbf0f7f04ee",
      "nick": "raxajaib",
      "premium": false,
      "totalLimit": 0,
      "limit": 100,
      "uang": 10000,
      "lastclaim": 1738344107034,
      "lastrampok": 1738344107034
    },
    "62895344491127@s.whatsapp.net": {
      "vip": false,
      "badword": 0,
      "title": "",
      "serialNumber": "fbd2d303ab9adffd0548d1bae2a814e6",
      "nick": "🤥",
      "premium": false,
      "totalLimit": 0,
      "limit": 100,
      "uang": 10000,
      "lastclaim": 1738344129548,
      "lastrampok": 1738344129548
    },
    "6281525717740@s.whatsapp.net": {
      "vip": false,
      "badword": 0,
      "title": "",
      "serialNumber": "24122758c960a6a08dc892edadc76e73",
      "nick": "Kevin",
      "premium": false,
      "totalLimit": 0,
      "limit": 100,
      "uang": 10000,
      "lastclaim": 1738344237486,
      "lastrampok": 1738344237486
    },
    "6283890224697@s.whatsapp.net": {
      "vip": false,
      "badword": 0,
      "title": "",
      "serialNumber": "8f5b096e0fb42a07d532feb89fed6ebd",
      "nick": "avvidence",
      "premium": false,
      "totalLimit": 0,
      "limit": 100,
      "uang": 10000,
      "lastclaim": 1738344277171,
      "lastrampok": 1738344277171
    },
    "6282249830993@s.whatsapp.net": {
      "vip": false,
      "badword": 0,
      "title": "",
      "serialNumber": "5b66da0d39299ed5acea9c8b24bb3165",
      "nick": "•_•",
      "premium": false,
      "totalLimit": 0,
      "limit": 100,
      "uang": 10000,
      "lastclaim": 1738344310511,
      "lastrampok": 1738344310511
    },
    "6285142709900@s.whatsapp.net": {
      "vip": false,
      "badword": 0,
      "title": "",
      "serialNumber": "b0e42a1a6b4b10628834d7f3835c0700",
      "nick": "iky",
      "premium": false,
      "totalLimit": 0,
      "limit": 100,
      "uang": 10000,
      "lastclaim": 1738344523624,
      "lastrampok": 1738344523624
    },
    "6287878772034@s.whatsapp.net": {
      "vip": false,
      "badword": 0,
      "title": "",
      "serialNumber": "35ffd226651d4219b387d938549bf1b2",
      "nick": ".",
      "premium": false,
      "totalLimit": 0,
      "limit": 100,
      "uang": 10000,
      "lastclaim": 1738344577598,
      "lastrampok": 1738344577598
    },
    "6285396925719@s.whatsapp.net": {
      "vip": false,
      "badword": 0,
      "title": "",
      "serialNumber": "5d6796390e29894dbe18d4f4e21ef8ae",
      "nick": "synn",
      "premium": false,
      "totalLimit": 0,
      "limit": 100,
      "uang": 10000,
      "lastclaim": 1738344581597,
      "lastrampok": 1738344581597
    },
    "6285885689740@s.whatsapp.net": {
      "vip": false,
      "badword": 0,
      "title": "",
      "serialNumber": "1bbeb0fa2aeac80c9225921cf8f48ace",
      "nick": "pp",
      "premium": false,
      "totalLimit": 0,
      "limit": 100,
      "uang": 10000,
      "lastclaim": 1738344705888,
      "lastrampok": 1738344705888
    },
    "6283844963472@s.whatsapp.net": {
      "vip": false,
      "badword": 0,
      "title": "",
      "serialNumber": "b8ab0ac82437613550f8f6f1a01892e1",
      "nick": "sin~",
      "premium": false,
      "totalLimit": 0,
      "limit": 100,
      "uang": 10000,
      "lastclaim": 1738344866212,
      "lastrampok": 1738344866212
    },
    "62882020682446@s.whatsapp.net": {
      "vip": false,
      "badword": 0,
      "title": "",
      "serialNumber": "6007913d5947867e03544e0a706cb21b",
      "nick": "Valdoo",
      "premium": false,
      "totalLimit": 0,
      "limit": 100,
      "uang": 10000,
      "lastclaim": 1738345027743,
      "lastrampok": 1738345027743
    },
    "6282211403673@s.whatsapp.net": {
      "vip": false,
      "badword": 0,
      "title": "",
      "serialNumber": "90201a2a2813d3eb34928f2f736860e2",
      "nick": "SUPERVynnn`",
      "premium": false,
      "totalLimit": 0,
      "limit": 100,
      "uang": 10000,
      "lastclaim": 1738345049534,
      "lastrampok": 1738345049534
    },
    "6289515732741@s.whatsapp.net": {
      "vip": false,
      "badword": 0,
      "title": "",
      "serialNumber": "2f2fce803907c4ca1356fc3f8223cad9",
      "nick": "*",
      "premium": false,
      "totalLimit": 0,
      "limit": 100,
      "uang": 10000,
      "lastclaim": 1738345096681,
      "lastrampok": 1738345096681
    },
    "6282141840915@s.whatsapp.net": {
      "vip": false,
      "badword": 0,
      "title": "",
      "serialNumber": "00fc8bbdd8ec6549fae9f405ceea35d8",
      "nick": "Danz",
      "premium": false,
      "totalLimit": 0,
      "limit": 100,
      "uang": 10000,
      "lastclaim": 1738345252598,
      "lastrampok": 1738345252598
    },
    "6289604477890@s.whatsapp.net": {
      "vip": false,
      "badword": 0,
      "title": "",
      "serialNumber": "6848d50f73ded54535910bf034544fb6",
      "nick": "hahahahaha",
      "premium": false,
      "totalLimit": 0,
      "limit": 100,
      "uang": 10000,
      "lastclaim": 1738345308565,
      "lastrampok": 1738345308565
    },
    "120363324729186842@newsletter": {
      "vip": false,
      "badword": 0,
      "title": "",
      "serialNumber": "635e00fba446ddb9afb92e7b343e7734",
      "premium": false,
      "totalLimit": 0,
      "limit": 100,
      "uang": 10000,
      "lastclaim": 1738345423160,
      "lastrampok": 1738345423160
    },
    "6282326292040@s.whatsapp.net": {
      "vip": false,
      "badword": 0,
      "title": "",
      "serialNumber": "32e67916ca6c053718b6a87eddf78652",
      "nick": "napos",
      "premium": false,
      "totalLimit": 0,
      "limit": 100,
      "uang": 10000,
      "lastclaim": 1738345424484,
      "lastrampok": 1738345424484
    },
    "6283186894617@s.whatsapp.net": {
      "vip": false,
      "badword": 0,
      "title": "",
      "serialNumber": "e6daa71a8a85a799c31977bd9c4fbcf7",
      "nick": "rakaa low",
      "premium": false,
      "totalLimit": 0,
      "limit": 100,
      "uang": 10000,
      "lastclaim": 1738345585795,
      "lastrampok": 1738345585795
    },
    "6285892938909@s.whatsapp.net": {
      "vip": false,
      "badword": 0,
      "title": "",
      "serialNumber": "e80a5c0acff4a4adc135db5c119a9c07",
      "nick": "jual akun-unchek-apk jb lainnya",
      "premium": false,
      "totalLimit": 0,
      "limit": 100,
      "uang": 10000,
      "lastclaim": 1738345662719,
      "lastrampok": 1738345662719
    },
    "62895343202235@s.whatsapp.net": {
      "vip": false,
      "badword": 0,
      "title": "",
      "serialNumber": "33b5e91ae99b6f8a907586e34e34386e",
      "nick": "banianjayyy",
      "premium": false,
      "totalLimit": 0,
      "limit": 100,
      "uang": 10000,
      "lastclaim": 1738345688876,
      "lastrampok": 1738345688876
    },
    "6285861178761@s.whatsapp.net": {
      "vip": false,
      "badword": 0,
      "title": "",
      "serialNumber": "a7117f895370d6d9c80137950ec873a6",
      "nick": "ccey ketua mapia",
      "premium": false,
      "totalLimit": 0,
      "limit": 100,
      "uang": 10000,
      "lastclaim": 1738346271436,
      "lastrampok": 1738346271436
    },
    "6282154954678@s.whatsapp.net": {
      "vip": false,
      "badword": 0,
      "title": "",
      "serialNumber": "2a297bbe38bed8f7eacde0bcf8797c37",
      "nick": "aran",
      "premium": false,
      "totalLimit": 0,
      "limit": 100,
      "uang": 10000,
      "lastclaim": 1738346346366,
      "lastrampok": 1738346346366
    },
    "6282326232078@s.whatsapp.net": {
      "vip": false,
      "badword": 0,
      "title": "",
      "serialNumber": "155902533fd066316e35f9134fea6965",
      "nick": "Mit",
      "premium": false,
      "totalLimit": 0,
      "limit": 100,
      "uang": 10000,
      "lastclaim": 1738346472518,
      "lastrampok": 1738346472518
    },
    "6285729429212@s.whatsapp.net": {
      "vip": false,
      "badword": 0,
      "title": "",
      "serialNumber": "6078868ae034a4c6f816b47e4415ce48",
      "nick": "joee",
      "premium": false,
      "totalLimit": 0,
      "limit": 100,
      "uang": 10000,
      "lastclaim": 1738346477192,
      "lastrampok": 1738346477192
    },
    "6283866447047@s.whatsapp.net": {
      "vip": false,
      "badword": 0,
      "title": "",
      "serialNumber": "98847d9cea8b36c77d1c29e6687404dc",
      "nick": "Sat",
      "premium": false,
      "totalLimit": 0,
      "limit": 100,
      "uang": 10000,
      "lastclaim": 1738346538182,
      "lastrampok": 1738346538182
    },
    "6281540030918@s.whatsapp.net": {
      "vip": false,
      "badword": 0,
      "title": "",
      "serialNumber": "8f61cc9177a0c76b75e0becfbfbfba8a",
      "nick": "ыфжж",
      "premium": false,
      "totalLimit": 0,
      "limit": 100,
      "uang": 10000,
      "lastclaim": 1738346873794,
      "lastrampok": 1738346873794
    },
    "6283114460812@s.whatsapp.net": {
      "vip": false,
      "badword": 0,
      "title": "",
      "serialNumber": "fccd4e63fdb2758fae2a14263f2894b4",
      "nick": "r",
      "premium": false,
      "totalLimit": 0,
      "limit": 100,
      "uang": 10000,
      "lastclaim": 1738347046516,
      "lastrampok": 1738347046516
    },
    "6289530505571@s.whatsapp.net": {
      "vip": false,
      "badword": 0,
      "title": "",
      "serialNumber": "8a485fe03bc1e0dc9980fe9c91338dc3",
      "nick": "efraim",
      "premium": false,
      "totalLimit": 0,
      "limit": 100,
      "uang": 10000,
      "lastclaim": 1738347200629,
      "lastrampok": 1738347200629
    },
    "6288801258409@s.whatsapp.net": {
      "vip": false,
      "badword": 0,
      "title": "",
      "serialNumber": "5a87c607778bdfb640925e0926f180fa",
      "nick": "YAS",
      "premium": false,
      "totalLimit": 0,
      "limit": 100,
      "uang": 10000,
      "lastclaim": 1738347208987,
      "lastrampok": 1738347208987
    },
    "6281287803085@s.whatsapp.net": {
      "vip": false,
      "badword": 0,
      "title": "",
      "serialNumber": "73ad5a7d9893997626e15c833d495cc7",
      "nick": "Ky",
      "premium": false,
      "totalLimit": 0,
      "limit": 100,
      "uang": 10000,
      "lastclaim": 1738347466757,
      "lastrampok": 1738347466757
    },
    "628976463278@s.whatsapp.net": {
      "vip": false,
      "badword": 0,
      "title": "",
      "serialNumber": "b3c0a337087f4aa79af65ca136e905b7",
      "nick": "𝖊 ᴠ 𝖆 𝖓",
      "premium": false,
      "totalLimit": 0,
      "limit": 100,
      "uang": 10000,
      "lastclaim": 1738347600712,
      "lastrampok": 1738347600712
    },
    "6283873751898@s.whatsapp.net": {
      "vip": false,
      "badword": 0,
      "title": "",
      "serialNumber": "a77ca0adce2c091aeb7526dabdff708b",
      "nick": "egiww cape kenon",
      "premium": false,
      "totalLimit": 0,
      "limit": 100,
      "uang": 10000,
      "lastclaim": 1738347834219,
      "lastrampok": 1738347834219
    },
    "628989105261@s.whatsapp.net": {
      "vip": false,
      "badword": 0,
      "title": "",
      "serialNumber": "02452fa288233f99b1091f1b21143399",
      "nick": "wannabeyours-",
      "premium": false,
      "totalLimit": 0,
      "limit": 100,
      "uang": 10000,
      "lastclaim": 1738347966081,
      "lastrampok": 1738347966081
    },
    "6288989658750@s.whatsapp.net": {
      "vip": false,
      "badword": 0,
      "title": "",
      "serialNumber": "289eaeb513aa30891c17cf39332b56c5",
      "nick": "-literasi",
      "premium": false,
      "totalLimit": 0,
      "limit": 100,
      "uang": 10000,
      "lastclaim": 1738348426954,
      "lastrampok": 1738348426954
    },
    "6281617476702@s.whatsapp.net": {
      "vip": false,
      "badword": 0,
      "title": "",
      "serialNumber": "92d6222913a67c99c507707f31d2215d",
      "nick": "yann",
      "premium": false,
      "totalLimit": 0,
      "limit": 100,
      "uang": 10000,
      "lastclaim": 1738348609890,
      "lastrampok": 1738348609890
    },
    "6285723734246@s.whatsapp.net": {
      "vip": false,
      "badword": 0,
      "title": "",
      "serialNumber": "26accef91e5cdf4809ce60937539f344",
      "nick": "toto",
      "premium": false,
      "totalLimit": 0,
      "limit": 100,
      "uang": 10000,
      "lastclaim": 1738348692061,
      "lastrampok": 1738348692061
    },
    "6281277602130@s.whatsapp.net": {
      "vip": false,
      "badword": 0,
      "title": "",
      "serialNumber": "e1340a5178bf62aa95171d0a189f0fdd",
      "nick": "faras",
      "premium": false,
      "totalLimit": 0,
      "limit": 100,
      "uang": 10000,
      "lastclaim": 1738348925345,
      "lastrampok": 1738348925345
    },
    "6285282052952@s.whatsapp.net": {
      "vip": false,
      "badword": 0,
      "title": "",
      "serialNumber": "bcc0188a56431a11941d7c720fe56adf",
      "nick": "𝘼𝙯𝙯𝙓𝘿",
      "premium": false,
      "totalLimit": 0,
      "limit": 100,
      "uang": 10000,
      "lastclaim": 1738349053633,
      "lastrampok": 1738349053633
    },
    "6285807117076@s.whatsapp.net": {
      "vip": false,
      "badword": 0,
      "title": "",
      "serialNumber": "416241b6eb98b3f6422575fd9efdf0ba",
      "nick": "#Nukii?",
      "premium": false,
      "totalLimit": 0,
      "limit": 100,
      "uang": 10000,
      "lastclaim": 1738349181767,
      "lastrampok": 1738349181767
    },
    "6282291491236@s.whatsapp.net": {
      "vip": false,
      "badword": 0,
      "title": "",
      "serialNumber": "8b2d9020cff85445d67f22497c025140",
      "nick": "wansmor",
      "premium": false,
      "totalLimit": 0,
      "limit": 100,
      "uang": 10000,
      "lastclaim": 1738349302082,
      "lastrampok": 1738349302082
    },
    "6287835420726@s.whatsapp.net": {
      "vip": false,
      "badword": 0,
      "title": "",
      "serialNumber": "44e0d1c2b593c9980199f32f8bef5b74",
      "nick": "meki",
      "premium": false,
      "totalLimit": 0,
      "limit": 100,
      "uang": 10000,
      "lastclaim": 1738349677889,
      "lastrampok": 1738349677889
    },
    "628992572853@s.whatsapp.net": {
      "vip": false,
      "badword": 0,
      "title": "",
      "serialNumber": "203447e83d797b656dd85ff2d0859dc8",
      "nick": "justin",
      "premium": false,
      "totalLimit": 0,
      "limit": 100,
      "uang": 10000,
      "lastclaim": 1738350133953,
      "lastrampok": 1738350133953
    },
    "6283865762703@s.whatsapp.net": {
      "vip": false,
      "badword": 0,
      "title": "",
      "serialNumber": "1d85728c68dbba55c103c72a298d7d8b",
      "nick": ".n.",
      "premium": false,
      "totalLimit": 0,
      "limit": 100,
      "uang": 10000,
      "lastclaim": 1738350237411,
      "lastrampok": 1738350237411
    },
    "6289655380202@s.whatsapp.net": {
      "vip": false,
      "badword": 0,
      "title": "",
      "serialNumber": "d707fdb8918da8fad34320636cec8fbd",
      "nick": "bimmm",
      "premium": false,
      "totalLimit": 0,
      "limit": 100,
      "uang": 10000,
      "lastclaim": 1738350333580,
      "lastrampok": 1738350333580
    },
    "6288242596873@s.whatsapp.net": {
      "vip": false,
      "badword": 0,
      "title": "",
      "serialNumber": "bd1c3a40c662c129fc0e70a1a45eb11f",
      "nick": "denta",
      "premium": false,
      "totalLimit": 0,
      "limit": 100,
      "uang": 10000,
      "lastclaim": 1738350379686,
      "lastrampok": 1738350379686
    },
    "6282143711728@s.whatsapp.net": {
      "vip": false,
      "badword": 0,
      "title": "",
      "serialNumber": "2be3af62a97ac5a36bc28264ce7a43e7",
      "nick": ".",
      "premium": false,
      "totalLimit": 0,
      "limit": 100,
      "uang": 10000,
      "lastclaim": 1738350731240,
      "lastrampok": 1738350731240
    },
    "62881024559546@s.whatsapp.net": {
      "vip": false,
      "badword": 0,
      "title": "",
      "serialNumber": "2833104fb56910e321a3440db3dcd391",
      "nick": "B.L.C",
      "premium": false,
      "totalLimit": 0,
      "limit": 100,
      "uang": 10000,
      "lastclaim": 1738350983025,
      "lastrampok": 1738350983025
    },
    "6285180733626@s.whatsapp.net": {
      "vip": false,
      "badword": 0,
      "title": "",
      "serialNumber": "a424330f78a1e60ab123161c8bb3111a",
      "nick": "ㅤ",
      "premium": false,
      "totalLimit": 0,
      "limit": 100,
      "uang": 10000,
      "lastclaim": 1738351124332,
      "lastrampok": 1738351124332
    },
    "62895360444110@s.whatsapp.net": {
      "vip": false,
      "badword": 0,
      "title": "",
      "serialNumber": "4c7444d298faea30da55f4ed8d91f188",
      "nick": "baree",
      "premium": false,
      "totalLimit": 0,
      "limit": 100,
      "uang": 10000,
      "lastclaim": 1738351140595,
      "lastrampok": 1738351140595
    },
    "6283146518755@s.whatsapp.net": {
      "vip": false,
      "badword": 0,
      "title": "",
      "serialNumber": "0c646ba3021b74c80aa1336eecef2d2f",
      "nick": "secret",
      "premium": false,
      "totalLimit": 0,
      "limit": 100,
      "uang": 10000,
      "lastclaim": 1738351345543,
      "lastrampok": 1738351345543
    },
    "120363301087120650@newsletter": {
      "vip": false,
      "badword": 0,
      "title": "",
      "serialNumber": "46131bfa3e758fe17bcbc139db0e116e",
      "premium": false,
      "totalLimit": 0,
      "limit": 100,
      "uang": 10000,
      "lastclaim": 1738351364522,
      "lastrampok": 1738351364522
    },
    "6285646615841@s.whatsapp.net": {
      "vip": false,
      "badword": 0,
      "title": "",
      "serialNumber": "707a40facce68a4051600a9f7f84bce2",
      "nick": "~zam",
      "premium": false,
      "totalLimit": 0,
      "limit": 100,
      "uang": 10000,
      "lastclaim": 1738351563489,
      "lastrampok": 1738351563489
    },
    "6283869027574@s.whatsapp.net": {
      "vip": false,
      "badword": 0,
      "title": "",
      "serialNumber": "fc20797cf4c8763812e874974a10c529",
      "nick": "keyyy",
      "premium": false,
      "totalLimit": 0,
      "limit": 100,
      "uang": 10000,
      "lastclaim": 1738351838677,
      "lastrampok": 1738351838677
    },
    "6289654242379@s.whatsapp.net": {
      "vip": false,
      "badword": 0,
      "title": "",
      "serialNumber": "c1c1d2f36b6ae1c8e566e4a7632c2cae",
      "nick": "dika",
      "premium": false,
      "totalLimit": 0,
      "limit": 100,
      "uang": 10000,
      "lastclaim": 1738351887628,
      "lastrampok": 1738351887628
    },
    "62895385964412@s.whatsapp.net": {
      "vip": false,
      "badword": 0,
      "title": "",
      "serialNumber": "ab73563c4b696eb42c000cf711ef2cbf",
      "nick": "belial",
      "premium": false,
      "totalLimit": 0,
      "limit": 100,
      "uang": 10000,
      "lastclaim": 1738352483589,
      "lastrampok": 1738352483589
    },
    "120363317025978926@newsletter": {
      "vip": false,
      "badword": 0,
      "title": "",
      "serialNumber": "8c42f9928abba277060cfc5a122b3b21",
      "premium": false,
      "totalLimit": 0,
      "limit": 100,
      "uang": 10000,
      "lastclaim": 1738352592045,
      "lastrampok": 1738352592045
    },
    "6285265941075@s.whatsapp.net": {
      "vip": false,
      "badword": 0,
      "title": "",
      "serialNumber": "5ea5519a9de38769c11fdb8c07d548c5",
      "nick": "t",
      "premium": false,
      "totalLimit": 0,
      "limit": 100,
      "uang": 10000,
      "lastclaim": 1738352819221,
      "lastrampok": 1738352819221
    },
    "6282289375352@s.whatsapp.net": {
      "vip": false,
      "badword": 0,
      "title": "",
      "serialNumber": "b09d045c4100e2e94fb353e7e253c292",
      "nick": "Pablo Escobar 👺",
      "premium": false,
      "totalLimit": 0,
      "limit": 100,
      "uang": 10000,
      "lastclaim": 1738353353037,
      "lastrampok": 1738353353037
    },
    "6281520416195@s.whatsapp.net": {
      "vip": false,
      "badword": 0,
      "title": "",
      "serialNumber": "9ed74cbcca778650d58ffa33e7747fa5",
      "nick": "jeff",
      "premium": false,
      "totalLimit": 0,
      "limit": 100,
      "uang": 10000,
      "lastclaim": 1738354187831,
      "lastrampok": 1738354187831
    },
    "120363317541350616@newsletter": {
      "vip": false,
      "badword": 0,
      "title": "",
      "serialNumber": "a1061394ab6a684a460c466f931a30a0",
      "premium": false,
      "totalLimit": 0,
      "limit": 100,
      "uang": 10000,
      "lastclaim": 1738354498805,
      "lastrampok": 1738354498805
    },
    "6285641161202@s.whatsapp.net": {
      "vip": false,
      "badword": 0,
      "title": "",
      "serialNumber": "9d5d4648aa5e86c58189b97ff8265a33",
      "nick": "~m!loveecipa",
      "premium": false,
      "totalLimit": 0,
      "limit": 100,
      "uang": 10000,
      "lastclaim": 1738355685964,
      "lastrampok": 1738355685964
    },
    "6285603358113@s.whatsapp.net": {
      "vip": false,
      "badword": 0,
      "title": "",
      "serialNumber": "05f7f8503063b7fc7bd2c9b152e43378",
      "nick": "farr.wazz",
      "premium": false,
      "totalLimit": 0,
      "limit": 100,
      "uang": 10000,
      "lastclaim": 1738355816229,
      "lastrampok": 1738355816229
    },
    "6285781198124@s.whatsapp.net": {
      "vip": false,
      "badword": 0,
      "title": "",
      "serialNumber": "229be3f556898551700dbe92399db29a",
      "nick": "??",
      "premium": false,
      "totalLimit": 0,
      "limit": 100,
      "uang": 10000,
      "lastclaim": 1738356160168,
      "lastrampok": 1738356160168
    },
    "6289674598539@s.whatsapp.net": {
      "vip": false,
      "badword": 0,
      "title": "",
      "serialNumber": "c58eb80c1b0943db6f2b7522e3ce657a",
      "nick": "Muhajir",
      "premium": false,
      "totalLimit": 0,
      "limit": 100,
      "uang": 10000,
      "lastclaim": 1738358156953,
      "lastrampok": 1738358156953
    },
    "6281291017114@s.whatsapp.net": {
      "vip": false,
      "badword": 0,
      "title": "",
      "serialNumber": "132c27703ae69e4c0774b44044ed29c0",
      "nick": "cL",
      "premium": false,
      "totalLimit": 0,
      "limit": 100,
      "uang": 10000,
      "lastclaim": 1738360323822,
      "lastrampok": 1738360323822
    },
    "6282266787674@s.whatsapp.net": {
      "vip": false,
      "badword": 0,
      "title": "",
      "serialNumber": "9f6f50b1f5964c96415264652c96fb06",
      "nick": ".",
      "premium": false,
      "totalLimit": 0,
      "limit": 100,
      "uang": 10000,
      "lastclaim": 1738360387811,
      "lastrampok": 1738360387811
    },
    "120363240237170669@newsletter": {
      "vip": false,
      "badword": 0,
      "title": "",
      "serialNumber": "bdf91fc3fc470dd8e60c9419975eae12",
      "premium": false,
      "totalLimit": 0,
      "limit": 100,
      "uang": 10000,
      "lastclaim": 1738360434751,
      "lastrampok": 1738360434751
    },
    "6285793732133@s.whatsapp.net": {
      "vip": false,
      "badword": 0,
      "title": "",
      "serialNumber": "4e238d924a5216702c34542361b31067",
      "nick": "Fadzx",
      "premium": false,
      "totalLimit": 0,
      "limit": 100,
      "uang": 10000,
      "lastclaim": 1738360552416,
      "lastrampok": 1738360552416
    },
    "6282225649147@s.whatsapp.net": {
      "vip": false,
      "badword": 0,
      "title": "",
      "serialNumber": "aca779a6ba2abba1466dc22fba1b4676",
      "nick": "Prinshel 💋💞",
      "premium": false,
      "totalLimit": 0,
      "limit": 100,
      "uang": 10000,
      "lastclaim": 1738360886233,
      "lastrampok": 1738360886233
    },
    "6285646550424@s.whatsapp.net": {
      "vip": false,
      "badword": 0,
      "title": "",
      "serialNumber": "21819c12fca3792218bdb95db5e8d921",
      "nick": "DILZSPIDERMEN",
      "premium": false,
      "totalLimit": 0,
      "limit": 100,
      "uang": 10000,
      "lastclaim": 1738361968810,
      "lastrampok": 1738361968810
    },
    "6283171790987@s.whatsapp.net": {
      "vip": false,
      "badword": 0,
      "title": "",
      "serialNumber": "a82a4c7a40f21193b9807877c32c671f",
      "nick": "107Fuzzy.",
      "premium": false,
      "totalLimit": 0,
      "limit": 100,
      "uang": 10000,
      "lastclaim": 1738362066335,
      "lastrampok": 1738362066335
    },
    "6287849379079@s.whatsapp.net": {
      "vip": false,
      "badword": 0,
      "title": "",
      "serialNumber": "bd8d349894351be58d43597a469773a7",
      "nick": "Rai.A",
      "premium": false,
      "totalLimit": 0,
      "limit": 100,
      "uang": 10000,
      "lastclaim": 1738362395253,
      "lastrampok": 1738362395253
    },
    "62895419666330@s.whatsapp.net": {
      "vip": false,
      "badword": 0,
      "title": "",
      "serialNumber": "4c183facb6d8eebcec43103989a61400",
      "nick": "Celz",
      "premium": false,
      "totalLimit": 0,
      "limit": 100,
      "uang": 10000,
      "lastclaim": 1738362517013,
      "lastrampok": 1738362517013
    },
    "6288975576131@s.whatsapp.net": {
      "vip": false,
      "badword": 0,
      "title": "",
      "serialNumber": "8dc130cebb1b9b037fc2cbc2757ff248",
      "nick": "Rafaell mc",
      "premium": false,
      "totalLimit": 0,
      "limit": 100,
      "uang": 10000,
      "lastclaim": 1738362552337,
      "lastrampok": 1738362552337
    },
    "6285382056170@s.whatsapp.net": {
      "vip": false,
      "badword": 0,
      "title": "",
      "serialNumber": "feeb17a0eb29753f2a22ee20eb631fde",
      "nick": "acaaa 🙆🏻‍♀️",
      "premium": false,
      "totalLimit": 0,
      "limit": 100,
      "uang": 10000,
      "lastclaim": 1738362874489,
      "lastrampok": 1738362874489
    },
    "6282159090420@s.whatsapp.net": {
      "vip": false,
      "badword": 0,
      "title": "",
      "serialNumber": "3dd0d9011ff49b0ac186ad92befd3f23",
      "nick": "𝟗𝟏𝟗hamzz",
      "premium": false,
      "totalLimit": 0,
      "limit": 100,
      "uang": 10000,
      "lastclaim": 1738363005076,
      "lastrampok": 1738363005076
    },
    "6283854683049@s.whatsapp.net": {
      "vip": false,
      "badword": 0,
      "title": "",
      "serialNumber": "11b1131718daea7c163d3ea882b49776",
      "nick": "iky ep",
      "premium": false,
      "totalLimit": 0,
      "limit": 100,
      "uang": 10000,
      "lastclaim": 1738363191134,
      "lastrampok": 1738363191134
    },
    "6283853460535@s.whatsapp.net": {
      "vip": false,
      "badword": 0,
      "title": "",
      "serialNumber": "b6c2fe1bfdf3e89e1d9de03102bb506c",
      "nick": "Rul",
      "premium": false,
      "totalLimit": 0,
      "limit": 100,
      "uang": 10000,
      "lastclaim": 1738363379755,
      "lastrampok": 1738363379755
    },
    "62881037148121@s.whatsapp.net": {
      "vip": false,
      "badword": 0,
      "title": "",
      "serialNumber": "29e6af2f864148fe2e91d73966bae7a0",
      "nick": "ulisss",
      "premium": false,
      "totalLimit": 0,
      "limit": 100,
      "uang": 10000,
      "lastclaim": 1738363607253,
      "lastrampok": 1738363607253
    },
    "6287853074607@s.whatsapp.net": {
      "vip": false,
      "badword": 0,
      "title": "",
      "serialNumber": "fa6293352f88ed127f05343a4cef70aa",
      "nick": "WHOOP",
      "premium": false,
      "totalLimit": 0,
      "limit": 100,
      "uang": 10000,
      "lastclaim": 1738363654840,
      "lastrampok": 1738363654840
    },
    "6287764962499@s.whatsapp.net": {
      "vip": false,
      "badword": 0,
      "title": "",
      "serialNumber": "8b85f14d2895178c793d959dceef98f3",
      "nick": "Ky?",
      "premium": false,
      "totalLimit": 0,
      "limit": 100,
      "uang": 10000,
      "lastclaim": 1738363844375,
      "lastrampok": 1738363844375
    },
    "62881037149445@s.whatsapp.net": {
      "vip": false,
      "badword": 0,
      "title": "",
      "serialNumber": "c0fbb0cfbf6b528297f23f6a50ba1ed7",
      "nick": "FREL",
      "premium": false,
      "totalLimit": 0,
      "limit": 100,
      "uang": 10000,
      "lastclaim": 1738363889530,
      "lastrampok": 1738363889530
    },
    "6288980052811@s.whatsapp.net": {
      "vip": false,
      "badword": 0,
      "title": "",
      "serialNumber": "6918e0b701565d1d1b4688413db146b7",
      "nick": "𝐂𝐞𝐲𝐥𝐚𝐚𝐚𝐃𝐊𝐊",
      "premium": false,
      "totalLimit": 0,
      "limit": 100,
      "uang": 10000,
      "lastclaim": 1738364319994,
      "lastrampok": 1738364319994
    },
    "6287754653420@s.whatsapp.net": {
      "vip": false,
      "badword": 0,
      "title": "",
      "serialNumber": "1e321cb1fdb566154a3a2f4169ea9afe",
      "nick": "nanaqt_",
      "premium": false,
      "totalLimit": 0,
      "limit": 100,
      "uang": 10000,
      "lastclaim": 1738364936277,
      "lastrampok": 1738364936277
    },
    "6288975412806@s.whatsapp.net": {
      "vip": false,
      "badword": 0,
      "title": "",
      "serialNumber": "e193579d8e448b72a664e2205cd4a68f",
      "nick": "Raxx",
      "premium": false,
      "totalLimit": 0,
      "limit": 100,
      "uang": 10000,
      "lastclaim": 1738364954326,
      "lastrampok": 1738364954326
    },
    "6281287267584@s.whatsapp.net": {
      "vip": false,
      "badword": 0,
      "title": "",
      "serialNumber": "58319e92674ce1bc3109cf08a7fe9b52",
      "nick": "Borilx Dawuan",
      "premium": false,
      "totalLimit": 0,
      "limit": 100,
      "uang": 10000,
      "lastclaim": 1738364989116,
      "lastrampok": 1738364989116
    },
    "6281351057891@s.whatsapp.net": {
      "vip": false,
      "badword": 0,
      "title": "",
      "serialNumber": "683de883dd540f44a7ff388dc0bf5479",
      "nick": "Ripa",
      "premium": false,
      "totalLimit": 0,
      "limit": 100,
      "uang": 10000,
      "lastclaim": 1738365101123,
      "lastrampok": 1738365101123
    },
    "6282148045794@s.whatsapp.net": {
      "vip": false,
      "badword": 0,
      "title": "",
      "serialNumber": "9912c3c153c5a2d73f413b853c619307",
      "nick": ".",
      "premium": false,
      "totalLimit": 0,
      "limit": 100,
      "uang": 10000,
      "lastclaim": 1738365119639,
      "lastrampok": 1738365119639
    },
    "6285742617544@s.whatsapp.net": {
      "vip": false,
      "badword": 0,
      "title": "",
      "serialNumber": "1ad9f25f2adb7620a79468fa605c4363",
      "nick": "uknown",
      "premium": false,
      "totalLimit": 0,
      "limit": 100,
      "uang": 10000,
      "lastclaim": 1738365258028,
      "lastrampok": 1738365258028
    },
    "6283848168706@s.whatsapp.net": {
      "vip": false,
      "badword": 0,
      "title": "",
      "serialNumber": "2e309e187b6a5e7b44f14284048cf8b6",
      "nick": "OWN FILE",
      "premium": false,
      "totalLimit": 0,
      "limit": 100,
      "uang": 10000,
      "lastclaim": 1738365314900,
      "lastrampok": 1738365314900
    },
    "6283853525369@s.whatsapp.net": {
      "vip": false,
      "badword": 0,
      "title": "",
      "serialNumber": "c5bf2be91143d40b34ffc14ca585d364",
      "nick": "ada!!",
      "premium": false,
      "totalLimit": 0,
      "limit": 100,
      "uang": 10000,
      "lastclaim": 1738365356805,
      "lastrampok": 1738365356805
    },
    "6285695914358@s.whatsapp.net": {
      "vip": false,
      "badword": 0,
      "title": "",
      "serialNumber": "f7ffaf98face8ab187e93c6db3ab5fe3",
      "nick": "Rendra",
      "premium": false,
      "totalLimit": 0,
      "limit": 100,
      "uang": 10000,
      "lastclaim": 1738365470495,
      "lastrampok": 1738365470495
    },
    "6281378670838@s.whatsapp.net": {
      "vip": false,
      "badword": 0,
      "title": "",
      "serialNumber": "d344313e2c253541436c0f3e7774b9c8",
      "nick": "zeye cantik",
      "premium": false,
      "totalLimit": 0,
      "limit": 100,
      "uang": 10000,
      "lastclaim": 1738365471625,
      "lastrampok": 1738365471625
    }
  },
  "chats": {
    "6287844551449@s.whatsapp.net": {
      "badword": false,
      "antiforeignnum": false,
      "antiviewonce": false,
      "antibot": false,
      "antispam": false,
      "antimedia": false,
      "antiimage": false,
      "antivideo": false,
      "antiaudio": false,
      "antisticker": false,
      "anticontact": false,
      "antilocation": false,
      "antidocument": false,
      "antilink": false,
      "antilinkgc": false,
      "mute": false
    },
    "120363206242850164@g.us": {
      "badword": false,
      "antiforeignnum": false,
      "antiviewonce": false,
      "antibot": false,
      "antispam": false,
      "antimedia": false,
      "antiimage": false,
      "antivideo": false,
      "antiaudio": false,
      "antisticker": false,
      "anticontact": false,
      "antilocation": false,
      "antidocument": false,
      "antilink": false,
      "antilinkgc": false,
      "mute": false
    },
    "120363312464118948@newsletter": {
      "badword": false,
      "antiforeignnum": false,
      "antiviewonce": false,
      "antibot": false,
      "antispam": false,
      "antimedia": false,
      "antiimage": false,
      "antivideo": false,
      "antiaudio": false,
      "antisticker": false,
      "anticontact": false,
      "antilocation": false,
      "antidocument": false,
      "antilink": false,
      "antilinkgc": false,
      "mute": false
    },
    "120363362956531641@g.us": {
      "badword": false,
      "antiforeignnum": false,
      "antiviewonce": false,
      "antibot": false,
      "antispam": false,
      "antimedia": false,
      "antiimage": false,
      "antivideo": false,
      "antiaudio": false,
      "antisticker": false,
      "anticontact": false,
      "antilocation": false,
      "antidocument": false,
      "antilink": false,
      "antilinkgc": false,
      "mute": false
    },
    "120363322409940857@g.us": {
      "badword": false,
      "antiforeignnum": false,
      "antiviewonce": false,
      "antibot": false,
      "antispam": false,
      "antimedia": false,
      "antiimage": false,
      "antivideo": false,
      "antiaudio": false,
      "antisticker": false,
      "anticontact": false,
      "antilocation": false,
      "antidocument": false,
      "antilink": false,
      "antilinkgc": false,
      "mute": false
    },
    "120363329057312461@g.us": {
      "badword": false,
      "antiforeignnum": false,
      "antiviewonce": false,
      "antibot": false,
      "antispam": false,
      "antimedia": false,
      "antiimage": false,
      "antivideo": false,
      "antiaudio": false,
      "antisticker": false,
      "anticontact": false,
      "antilocation": false,
      "antidocument": false,
      "antilink": false,
      "antilinkgc": false,
      "mute": false
    },
    "120363350339287927@g.us": {
      "badword": false,
      "antiforeignnum": false,
      "antiviewonce": false,
      "antibot": false,
      "antispam": false,
      "antimedia": false,
      "antiimage": false,
      "antivideo": false,
      "antiaudio": false,
      "antisticker": false,
      "anticontact": false,
      "antilocation": false,
      "antidocument": false,
      "antilink": false,
      "antilinkgc": false,
      "mute": false
    },
    "120363294372969918@g.us": {
      "badword": false,
      "antiforeignnum": false,
      "antiviewonce": false,
      "antibot": false,
      "antispam": false,
      "antimedia": false,
      "antiimage": false,
      "antivideo": false,
      "antiaudio": false,
      "antisticker": false,
      "anticontact": false,
      "antilocation": false,
      "antidocument": false,
      "antilink": false,
      "antilinkgc": false,
      "mute": false
    },
    "6285218836221-1617376542@g.us": {
      "badword": false,
      "antiforeignnum": false,
      "antiviewonce": false,
      "antibot": false,
      "antispam": false,
      "antimedia": false,
      "antiimage": false,
      "antivideo": false,
      "antiaudio": false,
      "antisticker": false,
      "anticontact": false,
      "antilocation": false,
      "antidocument": false,
      "antilink": false,
      "antilinkgc": false,
      "mute": false
    },
    "120363323896378788@g.us": {
      "badword": false,
      "antiforeignnum": false,
      "antiviewonce": false,
      "antibot": false,
      "antispam": false,
      "antimedia": false,
      "antiimage": false,
      "antivideo": false,
      "antiaudio": false,
      "antisticker": false,
      "anticontact": false,
      "antilocation": false,
      "antidocument": false,
      "antilink": false,
      "antilinkgc": false,
      "mute": false
    },
    "120363320597661428@g.us": {
      "badword": false,
      "antiforeignnum": false,
      "antiviewonce": false,
      "antibot": false,
      "antispam": false,
      "antimedia": false,
      "antiimage": false,
      "antivideo": false,
      "antiaudio": false,
      "antisticker": false,
      "anticontact": false,
      "antilocation": false,
      "antidocument": false,
      "antilink": false,
      "antilinkgc": false,
      "mute": false
    },
    "120363039082386818@g.us": {
      "badword": false,
      "antiforeignnum": false,
      "antiviewonce": false,
      "antibot": false,
      "antispam": false,
      "antimedia": false,
      "antiimage": false,
      "antivideo": false,
      "antiaudio": false,
      "antisticker": false,
      "anticontact": false,
      "antilocation": false,
      "antidocument": false,
      "antilink": false,
      "antilinkgc": false,
      "mute": false
    },
    "120363195955916136@g.us": {
      "badword": false,
      "antiforeignnum": false,
      "antiviewonce": false,
      "antibot": false,
      "antispam": false,
      "antimedia": false,
      "antiimage": false,
      "antivideo": false,
      "antiaudio": false,
      "antisticker": false,
      "anticontact": false,
      "antilocation": false,
      "antidocument": false,
      "antilink": false,
      "antilinkgc": false,
      "mute": false
    },
    "120363302583491012@newsletter": {
      "badword": false,
      "antiforeignnum": false,
      "antiviewonce": false,
      "antibot": false,
      "antispam": false,
      "antimedia": false,
      "antiimage": false,
      "antivideo": false,
      "antiaudio": false,
      "antisticker": false,
      "anticontact": false,
      "antilocation": false,
      "antidocument": false,
      "antilink": false,
      "antilinkgc": false,
      "mute": false
    },
    "120363344401749353@newsletter": {
      "badword": false,
      "antiforeignnum": false,
      "antiviewonce": false,
      "antibot": false,
      "antispam": false,
      "antimedia": false,
      "antiimage": false,
      "antivideo": false,
      "antiaudio": false,
      "antisticker": false,
      "anticontact": false,
      "antilocation": false,
      "antidocument": false,
      "antilink": false,
      "antilinkgc": false,
      "mute": false
    },
    "120363372909149226@g.us": {
      "badword": false,
      "antiforeignnum": false,
      "antiviewonce": false,
      "antibot": false,
      "antispam": false,
      "antimedia": false,
      "antiimage": false,
      "antivideo": false,
      "antiaudio": false,
      "antisticker": false,
      "anticontact": false,
      "antilocation": false,
      "antidocument": false,
      "antilink": false,
      "antilinkgc": false,
      "mute": false
    },
    "120363290964932754@g.us": {
      "badword": false,
      "antiforeignnum": false,
      "antiviewonce": false,
      "antibot": false,
      "antispam": false,
      "antimedia": false,
      "antiimage": false,
      "antivideo": false,
      "antiaudio": false,
      "antisticker": false,
      "anticontact": false,
      "antilocation": false,
      "antidocument": false,
      "antilink": false,
      "antilinkgc": false,
      "mute": false
    },
    "120363297141639102@g.us": {
      "badword": false,
      "antiforeignnum": false,
      "antiviewonce": false,
      "antibot": false,
      "antispam": false,
      "antimedia": false,
      "antiimage": false,
      "antivideo": false,
      "antiaudio": false,
      "antisticker": false,
      "anticontact": false,
      "antilocation": false,
      "antidocument": false,
      "antilink": false,
      "antilinkgc": false,
      "mute": false
    },
    "120363159552753674@newsletter": {
      "badword": false,
      "antiforeignnum": false,
      "antiviewonce": false,
      "antibot": false,
      "antispam": false,
      "antimedia": false,
      "antiimage": false,
      "antivideo": false,
      "antiaudio": false,
      "antisticker": false,
      "anticontact": false,
      "antilocation": false,
      "antidocument": false,
      "antilink": false,
      "antilinkgc": false,
      "mute": false
    },
    "120363321297746623@g.us": {
      "badword": false,
      "antiforeignnum": false,
      "antiviewonce": false,
      "antibot": false,
      "antispam": false,
      "antimedia": false,
      "antiimage": false,
      "antivideo": false,
      "antiaudio": false,
      "antisticker": false,
      "anticontact": false,
      "antilocation": false,
      "antidocument": false,
      "antilink": false,
      "antilinkgc": false,
      "mute": false
    },
    "120363324729186842@newsletter": {
      "badword": false,
      "antiforeignnum": false,
      "antiviewonce": false,
      "antibot": false,
      "antispam": false,
      "antimedia": false,
      "antiimage": false,
      "antivideo": false,
      "antiaudio": false,
      "antisticker": false,
      "anticontact": false,
      "antilocation": false,
      "antidocument": false,
      "antilink": false,
      "antilinkgc": false,
      "mute": false
    },
    "120363272055622034@g.us": {
      "badword": false,
      "antiforeignnum": false,
      "antiviewonce": false,
      "antibot": false,
      "antispam": false,
      "antimedia": false,
      "antiimage": false,
      "antivideo": false,
      "antiaudio": false,
      "antisticker": false,
      "anticontact": false,
      "antilocation": false,
      "antidocument": false,
      "antilink": false,
      "antilinkgc": false,
      "mute": false
    },
    "120363301087120650@newsletter": {
      "badword": false,
      "antiforeignnum": false,
      "antiviewonce": false,
      "antibot": false,
      "antispam": false,
      "antimedia": false,
      "antiimage": false,
      "antivideo": false,
      "antiaudio": false,
      "antisticker": false,
      "anticontact": false,
      "antilocation": false,
      "antidocument": false,
      "antilink": false,
      "antilinkgc": false,
      "mute": false
    },
    "120363317025978926@newsletter": {
      "badword": false,
      "antiforeignnum": false,
      "antiviewonce": false,
      "antibot": false,
      "antispam": false,
      "antimedia": false,
      "antiimage": false,
      "antivideo": false,
      "antiaudio": false,
      "antisticker": false,
      "anticontact": false,
      "antilocation": false,
      "antidocument": false,
      "antilink": false,
      "antilinkgc": false,
      "mute": false
    },
    "120363209214923769@g.us": {
      "badword": false,
      "antiforeignnum": false,
      "antiviewonce": false,
      "antibot": false,
      "antispam": false,
      "antimedia": false,
      "antiimage": false,
      "antivideo": false,
      "antiaudio": false,
      "antisticker": false,
      "anticontact": false,
      "antilocation": false,
      "antidocument": false,
      "antilink": false,
      "antilinkgc": false,
      "mute": false
    },
    "120363317541350616@newsletter": {
      "badword": false,
      "antiforeignnum": false,
      "antiviewonce": false,
      "antibot": false,
      "antispam": false,
      "antimedia": false,
      "antiimage": false,
      "antivideo": false,
      "antiaudio": false,
      "antisticker": false,
      "anticontact": false,
      "antilocation": false,
      "antidocument": false,
      "antilink": false,
      "antilinkgc": false,
      "mute": false
    },
    "120363348980689850@g.us": {
      "badword": false,
      "antiforeignnum": false,
      "antiviewonce": false,
      "antibot": false,
      "antispam": false,
      "antimedia": false,
      "antiimage": false,
      "antivideo": false,
      "antiaudio": false,
      "antisticker": false,
      "anticontact": false,
      "antilocation": false,
      "antidocument": false,
      "antilink": false,
      "antilinkgc": false,
      "mute": false
    },
    "120363347479081596@g.us": {
      "badword": false,
      "antiforeignnum": false,
      "antiviewonce": false,
      "antibot": false,
      "antispam": false,
      "antimedia": false,
      "antiimage": false,
      "antivideo": false,
      "antiaudio": false,
      "antisticker": false,
      "anticontact": false,
      "antilocation": false,
      "antidocument": false,
      "antilink": false,
      "antilinkgc": false,
      "mute": false
    },
    "120363240237170669@newsletter": {
      "badword": false,
      "antiforeignnum": false,
      "antiviewonce": false,
      "antibot": false,
      "antispam": false,
      "antimedia": false,
      "antiimage": false,
      "antivideo": false,
      "antiaudio": false,
      "antisticker": false,
      "anticontact": false,
      "antilocation": false,
      "antidocument": false,
      "antilink": false,
      "antilinkgc": false,
      "mute": false
    },
    "120363028302437537@g.us": {
      "badword": false,
      "antiforeignnum": false,
      "antiviewonce": false,
      "antibot": false,
      "antispam": false,
      "antimedia": false,
      "antiimage": false,
      "antivideo": false,
      "antiaudio": false,
      "antisticker": false,
      "anticontact": false,
      "antilocation": false,
      "antidocument": false,
      "antilink": false,
      "antilinkgc": false,
      "mute": false
    },
    "120363393384484052@g.us": {
      "badword": false,
      "antiforeignnum": false,
      "antiviewonce": false,
      "antibot": false,
      "antispam": false,
      "antimedia": false,
      "antiimage": false,
      "antivideo": false,
      "antiaudio": false,
      "antisticker": false,
      "anticontact": false,
      "antilocation": false,
      "antidocument": false,
      "antilink": false,
      "antilinkgc": false,
      "mute": false
    }
  },
  "settings": {
    "6287844551449@s.whatsapp.net": {
      "totalhit": 0,
      "totalError": 0,
      "online": false,
      "safesearch": false,
      "autosticker": false,
      "autodownload": false,
      "autobio": false,
      "autoread": false,
      "autorecordtype": false,
      "autorecord": false,
      "autotype": false,
      "autoblocknum": false,
      "onlygc": false,
      "onlypc": false,
      "watermark": {
        "packname": "Creator",
        "author": "Dcode-al"
      },
      "about": {
        "bot": {
          "nick": "+62 878-4455-1449",
          "alias": "Yaemiko MD"
        },
        "owner": {
          "nick": "+62 838-6704-2874",
          "alias": "6283867042874"
        }
      }
    }
  }
}