{
  "sticker": {},
  "database": {},
  "game": {},
  "others": {},
  "users": {
    "6282324262011@s.whatsapp.net": {
      "vip": false,
      "badword": 0,
      "title": "",
      "serialNumber": "7194553367bbacb8ab9b5e9176f6e1ef",
      "nick": "cicelyy",
      "premium": false,
      "totalLimit": 0,
      "limit": 99,
      "uang": 10000,
      "lastclaim": 1738249113948,
      "lastrampok": 1738249113948
    },
    "6287844551449@s.whatsapp.net": {
      "vip": false,
      "badword": 0,
      "title": "",
      "serialNumber": "42ca139fef6650f6a5e7ce3c993b28a5",
      "nick": "+62 878-4455-1449",
      "premium": false,
      "totalLimit": 0,
      "limit": 95,
      "uang": 10000,
      "lastclaim": 1738249121744,
      "lastrampok": 1738249121744
    },
    "6282132913643@s.whatsapp.net": {
      "vip": false,
      "badword": 0,
      "title": "",
      "serialNumber": "5d3ef2e6f31a3b0f9c80fa00e0a0bfd9",
      "nick": "ADMIN SHARE",
      "premium": false,
      "totalLimit": 0,
      "limit": 100,
      "uang": 10000,
      "lastclaim": 1738249124488,
      "lastrampok": 1738249124488
    },
    "6289653334368@s.whatsapp.net": {
      "vip": false,
      "badword": 0,
      "title": "",
      "serialNumber": "73dd58d9088dc8a699ee9e56d2a95022",
      "nick": ".....!",
      "premium": false,
      "totalLimit": 0,
      "limit": 100,
      "uang": 10000,
      "lastclaim": 1738249126147,
      "lastrampok": 1738249126147
    },
    "6285829372566@s.whatsapp.net": {
      "vip": false,
      "badword": 0,
      "title": "",
      "serialNumber": "01e26639ac78ef02f414fde74e347da9",
      "nick": "rein store",
      "premium": false,
      "totalLimit": 0,
      "limit": 100,
      "uang": 10000,
      "lastclaim": 1738249142214,
      "lastrampok": 1738249142214
    },
    "6285893399558@s.whatsapp.net": {
      "vip": false,
      "badword": 0,
      "title": "",
      "serialNumber": "e81244e928f855d6c86e69dd1be6e32b",
      "nick": "RYY NOPE 1 [9558]",
      "premium": false,
      "totalLimit": 0,
      "limit": 100,
      "uang": 10000,
      "lastclaim": 1738249142511,
      "lastrampok": 1738249142511
    },
    "6288744074204@s.whatsapp.net": {
      "vip": false,
      "badword": 0,
      "title": "",
      "serialNumber": "c414db1fc17a64f87a90cb6f19aff218",
      "nick": ".",
      "premium": false,
      "totalLimit": 0,
      "limit": 100,
      "uang": 10000,
      "lastclaim": 1738249142678,
      "lastrampok": 1738249142678
    },
    "628567101398@s.whatsapp.net": {
      "vip": false,
      "badword": 0,
      "title": "",
      "serialNumber": "fd03f1ee13f2aaa40f5259baac4bf13b",
      "nick": "MINZZ 2",
      "premium": false,
      "totalLimit": 0,
      "limit": 100,
      "uang": 10000,
      "lastclaim": 1738249154830,
      "lastrampok": 1738249154830
    },
    "6282384197682@s.whatsapp.net": {
      "vip": false,
      "badword": 0,
      "title": "",
      "serialNumber": "d8e8b046ea3daa73ba078ab9ca023141",
      "nick": "17Yexennn",
      "premium": false,
      "totalLimit": 0,
      "limit": 100,
      "uang": 10000,
      "lastclaim": 1738249155590,
      "lastrampok": 1738249155590
    },
    "120363312464118948@newsletter": {
      "vip": false,
      "badword": 0,
      "title": "",
      "serialNumber": "142222f94321e1b94b0d46364b64c432",
      "premium": false,
      "totalLimit": 0,
      "limit": 100,
      "uang": 10000,
      "lastclaim": 1738249158002,
      "lastrampok": 1738249158002
    },
    "62895373875060@s.whatsapp.net": {
      "vip": false,
      "badword": 0,
      "title": "",
      "serialNumber": "fc60c7a72ee6f3e53d7ca0d18e72212b",
      "nick": "juan",
      "premium": false,
      "totalLimit": 0,
      "limit": 100,
      "uang": 10000,
      "lastclaim": 1738249160429,
      "lastrampok": 1738249160429
    },
    "6281809242528@s.whatsapp.net": {
      "vip": false,
      "badword": 0,
      "title": "",
      "serialNumber": "a1df826d9feb65c15afa4c016683345c",
      "nick": "abcdimissyou",
      "premium": false,
      "totalLimit": 0,
      "limit": 100,
      "uang": 10000,
      "lastclaim": 1738249163400,
      "lastrampok": 1738249163400
    },
    "120363317025978926@newsletter": {
      "vip": false,
      "badword": 0,
      "title": "",
      "serialNumber": "36b02819dc6ffcca8e5f86056c28363f",
      "premium": false,
      "totalLimit": 0,
      "limit": 100,
      "uang": 10000,
      "lastclaim": 1738249164896,
      "lastrampok": 1738249164896
    },
    "6285890116766@s.whatsapp.net": {
      "vip": false,
      "badword": 0,
      "title": "",
      "serialNumber": "9163bdf9b8c7a14f3333a4d4dd4e68f7",
      "nick": "Jily",
      "premium": false,
      "totalLimit": 0,
      "limit": 100,
      "uang": 10000,
      "lastclaim": 1738249178535,
      "lastrampok": 1738249178535
    },
    "120363302583491012@newsletter": {
      "vip": false,
      "badword": 0,
      "title": "",
      "serialNumber": "22b4e1869ca86d357517075e947fa9df",
      "premium": false,
      "totalLimit": 0,
      "limit": 100,
      "uang": 10000,
      "lastclaim": 1738249178749,
      "lastrampok": 1738249178749
    },
    "6283139578685@s.whatsapp.net": {
      "vip": false,
      "badword": 0,
      "title": "",
      "serialNumber": "eed68a8e28381212178fb693aab35850",
      "nick": "shiro19%",
      "premium": false,
      "totalLimit": 0,
      "limit": 100,
      "uang": 10000,
      "lastclaim": 1738249184982,
      "lastrampok": 1738249184982
    },
    "6283849035243@s.whatsapp.net": {
      "vip": false,
      "badword": 0,
      "title": "",
      "serialNumber": "751fd515cd55cae0e0084d758fa6ad4a",
      "nick": "hánz★",
      "premium": false,
      "totalLimit": 0,
      "limit": 100,
      "uang": 10000,
      "lastclaim": 1738249185946,
      "lastrampok": 1738249185946
    },
    "6281287648175@s.whatsapp.net": {
      "vip": false,
      "badword": 0,
      "title": "",
      "serialNumber": "e08480271ec986d6d1e6dccbf09cedb4",
      "nick": "awen",
      "premium": false,
      "totalLimit": 0,
      "limit": 100,
      "uang": 10000,
      "lastclaim": 1738249187414,
      "lastrampok": 1738249187414
    },
    "6285261786109@s.whatsapp.net": {
      "vip": false,
      "badword": 0,
      "title": "",
      "serialNumber": "fdb3fb3e95c06fcfa5ecb94494af62a2",
      "nick": "Yann",
      "premium": false,
      "totalLimit": 0,
      "limit": 100,
      "uang": 10000,
      "lastclaim": 1738249242683,
      "lastrampok": 1738249242683
    },
    "6282148045794@s.whatsapp.net": {
      "vip": false,
      "badword": 0,
      "title": "",
      "serialNumber": "d7e7f830311ad27911a25f4cda2e7f07",
      "nick": ".",
      "premium": false,
      "totalLimit": 0,
      "limit": 100,
      "uang": 10000,
      "lastclaim": 1738249248072,
      "lastrampok": 1738249248072
    },
    "62895400673797@s.whatsapp.net": {
      "vip": false,
      "badword": 0,
      "title": "",
      "serialNumber": "31db8430de87cd5bc3514d6902e34c0f",
      "nick": "mnusia.",
      "premium": false,
      "totalLimit": 0,
      "limit": 100,
      "uang": 10000,
      "lastclaim": 1738249300039,
      "lastrampok": 1738249300039
    },
    "6283862707686@s.whatsapp.net": {
      "vip": false,
      "badword": 0,
      "title": "",
      "serialNumber": "9bf62976081bcbc63144a2f28038f8c8",
      "nick": "Bro",
      "premium": false,
      "totalLimit": 0,
      "limit": 100,
      "uang": 10000,
      "lastclaim": 1738249309552,
      "lastrampok": 1738249309552
    },
    "6283846432993@s.whatsapp.net": {
      "vip": false,
      "badword": 0,
      "title": "",
      "serialNumber": "93e4fb23f3cde172fdde61f9508960b6",
      "nick": "junaa",
      "premium": false,
      "totalLimit": 0,
      "limit": 100,
      "uang": 10000,
      "lastclaim": 1738249311507,
      "lastrampok": 1738249311507
    },
    "6282286332801@s.whatsapp.net": {
      "vip": false,
      "badword": 0,
      "title": "",
      "serialNumber": "742ae0b67a527cc53d29c8127a8df86f",
      "nick": "febry",
      "premium": false,
      "totalLimit": 0,
      "limit": 100,
      "uang": 10000,
      "lastclaim": 1738249313682,
      "lastrampok": 1738249313682
    },
    "6282299030520@s.whatsapp.net": {
      "vip": false,
      "badword": 0,
      "title": "",
      "serialNumber": "ca5124744f51fc4261bfdfcb50233609",
      "nick": "𝙧𝙖𝙝𝙯",
      "premium": false,
      "totalLimit": 0,
      "limit": 100,
      "uang": 10000,
      "lastclaim": 1738249323621,
      "lastrampok": 1738249323621
    },
    "6282123275511@s.whatsapp.net": {
      "vip": false,
      "badword": 0,
      "title": "",
      "serialNumber": "6afb2e2323e3fa3e6eaa811dad27715a",
      "nick": "KIYASH",
      "premium": false,
      "totalLimit": 0,
      "limit": 100,
      "uang": 10000,
      "lastclaim": 1738249324199,
      "lastrampok": 1738249324199
    },
    "6285764101691@s.whatsapp.net": {
      "vip": false,
      "badword": 0,
      "title": "",
      "serialNumber": "81c71f061c34f8b66bad72f26edf0caf",
      "nick": "rrr",
      "premium": false,
      "totalLimit": 0,
      "limit": 100,
      "uang": 10000,
      "lastclaim": 1738249325801,
      "lastrampok": 1738249325801
    },
    "6289515569752@s.whatsapp.net": {
      "vip": false,
      "badword": 0,
      "title": "",
      "serialNumber": "9783e3e1d85d4e487b427f5bad908dc2",
      "nick": "ABYY",
      "premium": false,
      "totalLimit": 0,
      "limit": 100,
      "uang": 10000,
      "lastclaim": 1738249337595,
      "lastrampok": 1738249337595
    },
    "120363344401749353@newsletter": {
      "vip": false,
      "badword": 0,
      "title": "",
      "serialNumber": "a20f9b3e89d7439dea187fb45564e3a1",
      "premium": false,
      "totalLimit": 0,
      "limit": 100,
      "uang": 10000,
      "lastclaim": 1738249340051,
      "lastrampok": 1738249340051
    },
    "6281248590570@s.whatsapp.net": {
      "vip": false,
      "badword": 0,
      "title": "",
      "serialNumber": "6cd741ef99b437e772f1a38240b0c1cc",
      "nick": "Tuan Kentzyy.",
      "premium": false,
      "totalLimit": 0,
      "limit": 100,
      "uang": 10000,
      "lastclaim": 1738249349740,
      "lastrampok": 1738249349740
    },
    "6285339008670@s.whatsapp.net": {
      "vip": false,
      "badword": 0,
      "title": "",
      "serialNumber": "1c46d271f4db5b6a1798049eaf11d5cc",
      "nick": "~",
      "premium": false,
      "totalLimit": 0,
      "limit": 100,
      "uang": 10000,
      "lastclaim": 1738249375356,
      "lastrampok": 1738249375356
    },
    "6281430345075@s.whatsapp.net": {
      "vip": false,
      "badword": 0,
      "title": "",
      "serialNumber": "30651cec0a3fb8ebc253352c1438866e",
      "nick": "BANG MAUL REAL",
      "premium": false,
      "totalLimit": 0,
      "limit": 100,
      "uang": 10000,
      "lastclaim": 1738249378366,
      "lastrampok": 1738249378366
    },
    "6287774130557@s.whatsapp.net": {
      "vip": false,
      "badword": 0,
      "title": "",
      "serialNumber": "e797ed989b32ebb030c51dce96088e78",
      "nick": "🔮",
      "premium": false,
      "totalLimit": 0,
      "limit": 100,
      "uang": 10000,
      "lastclaim": 1738249412487,
      "lastrampok": 1738249412487
    },
    "62895419666330@s.whatsapp.net": {
      "vip": false,
      "badword": 0,
      "title": "",
      "serialNumber": "db03cda61d1520f46daa452258a7b8b9",
      "nick": "Celz",
      "premium": false,
      "totalLimit": 0,
      "limit": 100,
      "uang": 10000,
      "lastclaim": 1738249416047,
      "lastrampok": 1738249416047
    },
    "6285624244207@s.whatsapp.net": {
      "vip": false,
      "badword": 0,
      "title": "",
      "serialNumber": "aa4f9f66fd86960b70a66633df82b6dc",
      "nick": "Recxy",
      "premium": false,
      "totalLimit": 0,
      "limit": 100,
      "uang": 10000,
      "lastclaim": 1738249432489,
      "lastrampok": 1738249432489
    },
    "6285870403122@s.whatsapp.net": {
      "vip": false,
      "badword": 0,
      "title": "",
      "serialNumber": "86908777289c78c310a37c427b7a6df3",
      "nick": "z",
      "premium": false,
      "totalLimit": 0,
      "limit": 100,
      "uang": 10000,
      "lastclaim": 1738249433331,
      "lastrampok": 1738249433331
    },
    "6281228978256@s.whatsapp.net": {
      "vip": false,
      "badword": 0,
      "title": "",
      "serialNumber": "52343e03f1c73064a02c6b714ed00e0a",
      "nick": "cjney parker",
      "premium": false,
      "totalLimit": 0,
      "limit": 100,
      "uang": 10000,
      "lastclaim": 1738249440533,
      "lastrampok": 1738249440533
    },
    "6282170607427@s.whatsapp.net": {
      "vip": false,
      "badword": 0,
      "title": "",
      "serialNumber": "e1119cda455e6a8efee0619d8bd6b9f0",
      "nick": "🤯",
      "premium": false,
      "totalLimit": 0,
      "limit": 100,
      "uang": 10000,
      "lastclaim": 1738249444579,
      "lastrampok": 1738249444579
    },
    "6282322409108@s.whatsapp.net": {
      "vip": false,
      "badword": 0,
      "title": "",
      "serialNumber": "474ddc87dbf04ddb8fdf7a9074aa8b72",
      "nick": ".",
      "premium": false,
      "totalLimit": 0,
      "limit": 100,
      "uang": 10000,
      "lastclaim": 1738249459405,
      "lastrampok": 1738249459405
    },
    "6285655600879@s.whatsapp.net": {
      "vip": false,
      "badword": 0,
      "title": "",
      "serialNumber": "e93faa14acdd1a4e5b35ef74c3c22849",
      "nick": "javierngab",
      "premium": false,
      "totalLimit": 0,
      "limit": 100,
      "uang": 10000,
      "lastclaim": 1738249482436,
      "lastrampok": 1738249482436
    },
    "6282143766775@s.whatsapp.net": {
      "vip": false,
      "badword": 0,
      "title": "",
      "serialNumber": "8047b8edf3544cf686ad439f932379e6",
      "nick": "Tirrzzz OWN BURBERRY GB 3",
      "premium": false,
      "totalLimit": 0,
      "limit": 100,
      "uang": 10000,
      "lastclaim": 1738249483265,
      "lastrampok": 1738249483265
    },
    "6289508007097@s.whatsapp.net": {
      "vip": false,
      "badword": 0,
      "title": "",
      "serialNumber": "0faf43ab5ea37422171e99689f78b2d4",
      "nick": "puputra",
      "premium": false,
      "totalLimit": 0,
      "limit": 100,
      "uang": 10000,
      "lastclaim": 1738249489373,
      "lastrampok": 1738249489373
    },
    "6285766342236@s.whatsapp.net": {
      "vip": false,
      "badword": 0,
      "title": "",
      "serialNumber": "26b724348e39238d3d4ac4098bca3d99",
      "nick": "PT FILE",
      "premium": false,
      "totalLimit": 0,
      "limit": 100,
      "uang": 10000,
      "lastclaim": 1738249499452,
      "lastrampok": 1738249499452
    },
    "6282275078239@s.whatsapp.net": {
      "vip": false,
      "badword": 0,
      "title": "",
      "serialNumber": "b8ece71d5b470b3244744e4ce17e1fe8",
      "nick": "GEO mc [own] #1",
      "premium": false,
      "totalLimit": 0,
      "limit": 100,
      "uang": 10000,
      "lastclaim": 1738249583250,
      "lastrampok": 1738249583250
    },
    "120363346414594923@newsletter": {
      "vip": false,
      "badword": 0,
      "title": "",
      "serialNumber": "2617655e443400fa6b1e3d34376685ad",
      "premium": false,
      "totalLimit": 0,
      "limit": 100,
      "uang": 10000,
      "lastclaim": 1738249596857,
      "lastrampok": 1738249596857
    },
    "6285708262293@s.whatsapp.net": {
      "vip": false,
      "badword": 0,
      "title": "",
      "serialNumber": "732248467d239d714ff1555eb8251746",
      "nick": "Aby",
      "premium": false,
      "totalLimit": 0,
      "limit": 100,
      "uang": 10000,
      "lastclaim": 1738249606397,
      "lastrampok": 1738249606397
    },
    "6283833649523@s.whatsapp.net": {
      "vip": false,
      "badword": 0,
      "title": "",
      "serialNumber": "c872e55d2f98b7039793b9b1128e5fdc",
      "nick": "fanzzz  PGLT👾 [414]",
      "premium": false,
      "totalLimit": 0,
      "limit": 100,
      "uang": 10000,
      "lastclaim": 1738249624875,
      "lastrampok": 1738249624875
    },
    "6282111128440@s.whatsapp.net": {
      "vip": false,
      "badword": 0,
      "title": "",
      "serialNumber": "3ce6783d47300907f4f90c0d25bcf13f",
      "nick": "kunto",
      "premium": false,
      "totalLimit": 0,
      "limit": 100,
      "uang": 10000,
      "lastclaim": 1738249629591,
      "lastrampok": 1738249629591
    },
    "628386409626@s.whatsapp.net": {
      "vip": false,
      "badword": 0,
      "title": "",
      "serialNumber": "1feefb912f309012dd9669a18f5c786a",
      "nick": "Rif",
      "premium": false,
      "totalLimit": 0,
      "limit": 100,
      "uang": 10000,
      "lastclaim": 1738249630594,
      "lastrampok": 1738249630594
    },
    "6281398664885@s.whatsapp.net": {
      "vip": false,
      "badword": 0,
      "title": "",
      "serialNumber": "b935b2562ed00bbb5c307028436632fe",
      "nick": "ghaisan",
      "premium": false,
      "totalLimit": 0,
      "limit": 100,
      "uang": 10000,
      "lastclaim": 1738249636435,
      "lastrampok": 1738249636435
    },
    "6282328815713@s.whatsapp.net": {
      "vip": false,
      "badword": 0,
      "title": "",
      "serialNumber": "572e6e8cabe9282c493f7fa397f23d91",
      "nick": "omayygatt jihaannnn🤍",
      "premium": false,
      "totalLimit": 0,
      "limit": 100,
      "uang": 10000,
      "lastclaim": 1738249644689,
      "lastrampok": 1738249644689
    },
    "6289635546914@s.whatsapp.net": {
      "vip": false,
      "badword": 0,
      "title": "",
      "serialNumber": "dde37078a1d4ee1af5bf1c2f9b9d2399",
      "nick": "zora",
      "premium": false,
      "totalLimit": 0,
      "limit": 100,
      "uang": 10000,
      "lastclaim": 1738249645087,
      "lastrampok": 1738249645087
    },
    "6283847884883@s.whatsapp.net": {
      "vip": false,
      "badword": 0,
      "title": "",
      "serialNumber": "2ab64b06a924480c8a5c55d4bf2fc00a",
      "nick": "kela",
      "premium": false,
      "totalLimit": 0,
      "limit": 100,
      "uang": 10000,
      "lastclaim": 1738249668131,
      "lastrampok": 1738249668131
    },
    "628568430778@s.whatsapp.net": {
      "vip": false,
      "badword": 0,
      "title": "",
      "serialNumber": "af52fc47faaf3259f19439608062fdc7",
      "nick": "16apinzZz",
      "premium": false,
      "totalLimit": 0,
      "limit": 100,
      "uang": 10000,
      "lastclaim": 1738249697969,
      "lastrampok": 1738249697969
    },
    "6285212929993@s.whatsapp.net": {
      "vip": false,
      "badword": 0,
      "title": "",
      "serialNumber": "68b170ff2902b9a27bfba56d50ad39c0",
      "nick": "reno syilok",
      "premium": false,
      "totalLimit": 0,
      "limit": 100,
      "uang": 10000,
      "lastclaim": 1738249713803,
      "lastrampok": 1738249713803
    },
    "120363198075123857@newsletter": {
      "vip": false,
      "badword": 0,
      "title": "",
      "serialNumber": "789dc0ad7fcadd9b0577150aac53067d",
      "premium": false,
      "totalLimit": 0,
      "limit": 100,
      "uang": 10000,
      "lastclaim": 1738249719601,
      "lastrampok": 1738249719601
    },
    "6285361379996@s.whatsapp.net": {
      "vip": false,
      "badword": 0,
      "title": "",
      "serialNumber": "bf2a5e7e5d1c7416e4604c4c0d2cfdd7",
      "nick": "L",
      "premium": false,
      "totalLimit": 0,
      "limit": 100,
      "uang": 10000,
      "lastclaim": 1738249724541,
      "lastrampok": 1738249724541
    },
    "6282177880914@s.whatsapp.net": {
      "vip": false,
      "badword": 0,
      "title": "",
      "serialNumber": "465a7064f6096e0851edead6e9a165a5",
      "nick": "g",
      "premium": false,
      "totalLimit": 0,
      "limit": 100,
      "uang": 10000,
      "lastclaim": 1738249745794,
      "lastrampok": 1738249745794
    },
    "62895415223739@s.whatsapp.net": {
      "vip": false,
      "badword": 0,
      "title": "",
      "serialNumber": "40d9ca895bbc5d7a6f7e7f5a51016708",
      "nick": "niavy",
      "premium": false,
      "totalLimit": 0,
      "limit": 100,
      "uang": 10000,
      "lastclaim": 1738249755665,
      "lastrampok": 1738249755665
    },
    "6283852921274@s.whatsapp.net": {
      "vip": false,
      "badword": 0,
      "title": "",
      "serialNumber": "b980733b5d2bcb1c39e8c6f6141a9850",
      "nick": "Cilgo Store",
      "premium": false,
      "totalLimit": 0,
      "limit": 99,
      "uang": 10000,
      "lastclaim": 1738249770941,
      "lastrampok": 1738249770941
    },
    "6289518762660@s.whatsapp.net": {
      "vip": false,
      "badword": 0,
      "title": "",
      "serialNumber": "c125b872b96165928da2cda3de61f4be",
      "nick": "rizky",
      "premium": false,
      "totalLimit": 0,
      "limit": 100,
      "uang": 10000,
      "lastclaim": 1738249773729,
      "lastrampok": 1738249773729
    },
    "6282211403673@s.whatsapp.net": {
      "vip": false,
      "badword": 0,
      "title": "",
      "serialNumber": "608fc264d27ab93efe8df76cd9db2553",
      "nick": "SUPERVynnn`",
      "premium": false,
      "totalLimit": 0,
      "limit": 100,
      "uang": 10000,
      "lastclaim": 1738249844071,
      "lastrampok": 1738249844071
    },
    "6288973314771@s.whatsapp.net": {
      "vip": false,
      "badword": 0,
      "title": "",
      "serialNumber": "d0640d825a16ad85ae71be978d8cf694",
      "nick": "CHEZZY",
      "premium": false,
      "totalLimit": 0,
      "limit": 100,
      "uang": 10000,
      "lastclaim": 1738249852425,
      "lastrampok": 1738249852425
    },
    "6288708459005@s.whatsapp.net": {
      "vip": false,
      "badword": 0,
      "title": "",
      "serialNumber": "916fdc39e846aba3267638208867f883",
      "nick": "nickx",
      "premium": false,
      "totalLimit": 0,
      "limit": 100,
      "uang": 10000,
      "lastclaim": 1738249856930,
      "lastrampok": 1738249856930
    },
    "6285123981486@s.whatsapp.net": {
      "vip": false,
      "badword": 0,
      "title": "",
      "serialNumber": "12dc5eaaa09a503c8afb939e2d35b354",
      "nick": ".",
      "premium": false,
      "totalLimit": 0,
      "limit": 100,
      "uang": 10000,
      "lastclaim": 1738249861349,
      "lastrampok": 1738249861349
    },
    "6282231074198@s.whatsapp.net": {
      "vip": false,
      "badword": 0,
      "title": "",
      "serialNumber": "ff3de5ddf5855faa7bdc879cf8ee4970",
      "nick": "ㅤㅤㅤ ㅤ ",
      "premium": false,
      "totalLimit": 0,
      "limit": 100,
      "uang": 10000,
      "lastclaim": 1738249868709,
      "lastrampok": 1738249868709
    },
    "6281248688911@s.whatsapp.net": {
      "vip": false,
      "badword": 0,
      "title": "",
      "serialNumber": "fc854a7d52d4d7375686b83378d182ed",
      "nick": "pacehanzz",
      "premium": false,
      "totalLimit": 0,
      "limit": 100,
      "uang": 10000,
      "lastclaim": 1738249890920,
      "lastrampok": 1738249890920
    },
    "6281556664038@s.whatsapp.net": {
      "vip": false,
      "badword": 0,
      "title": "",
      "serialNumber": "7bbaf230f6cc84b3f5746243af6632b6",
      "nick": "PAIZ SERXCIUZ",
      "premium": false,
      "totalLimit": 0,
      "limit": 100,
      "uang": 10000,
      "lastclaim": 1738249906806,
      "lastrampok": 1738249906806
    },
    "6287894434065@s.whatsapp.net": {
      "vip": false,
      "badword": 0,
      "title": "",
      "serialNumber": "86d603ae5f649ae0b9fabc31b5e84553",
      "nick": "jaki Real",
      "premium": false,
      "totalLimit": 0,
      "limit": 100,
      "uang": 10000,
      "lastclaim": 1738249913778,
      "lastrampok": 1738249913778
    },
    "6282318175916@s.whatsapp.net": {
      "vip": false,
      "badword": 0,
      "title": "",
      "serialNumber": "7cbb6fa37f2b2c4911bfc89a1885ac6e",
      "nick": "zyzysigma?",
      "premium": false,
      "totalLimit": 0,
      "limit": 100,
      "uang": 10000,
      "lastclaim": 1738249917383,
      "lastrampok": 1738249917383
    },
    "6283869658736@s.whatsapp.net": {
      "vip": false,
      "badword": 0,
      "title": "",
      "serialNumber": "dc9fbecd23f691cbcf9ff2c0f3d442a9",
      "nick": "#toeng",
      "premium": false,
      "totalLimit": 0,
      "limit": 100,
      "uang": 10000,
      "lastclaim": 1738249922692,
      "lastrampok": 1738249922692
    },
    "6285737062822@s.whatsapp.net": {
      "vip": false,
      "badword": 0,
      "title": "",
      "serialNumber": "f7c8af9aa57204712064a99e0ed7dd07",
      "nick": "KELL",
      "premium": false,
      "totalLimit": 0,
      "limit": 100,
      "uang": 10000,
      "lastclaim": 1738249924820,
      "lastrampok": 1738249924820
    },
    "6281244935582@s.whatsapp.net": {
      "vip": false,
      "badword": 0,
      "title": "",
      "serialNumber": "be6e4c592181ab9ceb83d5e4b59bfcdb",
      "nick": "Gyn🇵🇸🇵🇸",
      "premium": false,
      "totalLimit": 0,
      "limit": 100,
      "uang": 10000,
      "lastclaim": 1738249926571,
      "lastrampok": 1738249926571
    },
    "6285711258331@s.whatsapp.net": {
      "vip": false,
      "badword": 0,
      "title": "",
      "serialNumber": "5afc745ebb32717287bec9337946f258",
      "nick": "𝐍αᑯ𝗂𐓣𝖾 🥨",
      "premium": false,
      "totalLimit": 0,
      "limit": 100,
      "uang": 10000,
      "lastclaim": 1738249927195,
      "lastrampok": 1738249927195
    },
    "6287827903060@s.whatsapp.net": {
      "vip": false,
      "badword": 0,
      "title": "",
      "serialNumber": "759642e24e59734fce6e9053dd5571f8",
      "nick": "𝑲𝑰𝑵𝑮 𝑽𝑨𝑵𝒁 [ 𝑴𝑰𝑳𝑶 ]",
      "premium": false,
      "totalLimit": 0,
      "limit": 100,
      "uang": 10000,
      "lastclaim": 1738249927723,
      "lastrampok": 1738249927723
    },
    "6282210596136@s.whatsapp.net": {
      "vip": false,
      "badword": 0,
      "title": "",
      "serialNumber": "1f7429694ac37356b9098570a59c1b4a",
      "nick": "a",
      "premium": false,
      "totalLimit": 0,
      "limit": 100,
      "uang": 10000,
      "lastclaim": 1738249934141,
      "lastrampok": 1738249934141
    },
    "6287761482277@s.whatsapp.net": {
      "vip": false,
      "badword": 0,
      "title": "",
      "serialNumber": "ab197027c9f1dcea56557dfc353a330a",
      "nick": "n",
      "premium": false,
      "totalLimit": 0,
      "limit": 100,
      "uang": 10000,
      "lastclaim": 1738249935784,
      "lastrampok": 1738249935784
    },
    "6283853525369@s.whatsapp.net": {
      "vip": false,
      "badword": 0,
      "title": "",
      "serialNumber": "4ed4907613ef942a35da831b5900199b",
      "nick": "ada!!",
      "premium": false,
      "totalLimit": 0,
      "limit": 100,
      "uang": 10000,
      "lastclaim": 1738249938963,
      "lastrampok": 1738249938963
    },
    "6288297912955@s.whatsapp.net": {
      "vip": false,
      "badword": 0,
      "title": "",
      "serialNumber": "aea471c0ea713bd0d948221849218cb7",
      "nick": ".",
      "premium": false,
      "totalLimit": 0,
      "limit": 100,
      "uang": 10000,
      "lastclaim": 1738249939647,
      "lastrampok": 1738249939647
    },
    "6281392623620@s.whatsapp.net": {
      "vip": false,
      "badword": 0,
      "title": "",
      "serialNumber": "9e23e20a8c18e90e908811f695c74757",
      "nick": "𝖑à",
      "premium": false,
      "totalLimit": 0,
      "limit": 100,
      "uang": 10000,
      "lastclaim": 1738249941372,
      "lastrampok": 1738249941372
    },
    "628119981516@s.whatsapp.net": {
      "vip": false,
      "badword": 0,
      "title": "",
      "serialNumber": "7141b7e1841ef591c8121c4aeaff302d",
      "nick": "Putri Zahrana",
      "premium": false,
      "totalLimit": 0,
      "limit": 100,
      "uang": 10000,
      "lastclaim": 1738249944780,
      "lastrampok": 1738249944780
    },
    "6285788587038@s.whatsapp.net": {
      "vip": false,
      "badword": 0,
      "title": "",
      "serialNumber": "2ca43cee7baecc370f7fd24f2c6f62f0",
      "nick": "Juan😺🤍",
      "premium": false,
      "totalLimit": 0,
      "limit": 100,
      "uang": 10000,
      "lastclaim": 1738249946672,
      "lastrampok": 1738249946672
    },
    "6283186293385@s.whatsapp.net": {
      "vip": false,
      "badword": 0,
      "title": "",
      "serialNumber": "da1a5238c7b92ce0be5ff1c061364b57",
      "nick": "kiyy",
      "premium": false,
      "totalLimit": 0,
      "limit": 100,
      "uang": 10000,
      "lastclaim": 1738249971517,
      "lastrampok": 1738249971517
    },
    "6282239880203@s.whatsapp.net": {
      "vip": false,
      "badword": 0,
      "title": "",
      "serialNumber": "2312e22fda7e7c77d2f9667d67d82972",
      "nick": "MANG AJI LAGA [ 0203 ]",
      "premium": false,
      "totalLimit": 0,
      "limit": 100,
      "uang": 10000,
      "lastclaim": 1738249981836,
      "lastrampok": 1738249981836
    },
    "6285396925719@s.whatsapp.net": {
      "vip": false,
      "badword": 0,
      "title": "",
      "serialNumber": "97e009c1b79c0c6b1b0e0d482763e1b1",
      "nick": "synn",
      "premium": false,
      "totalLimit": 0,
      "limit": 100,
      "uang": 10000,
      "lastclaim": 1738249982149,
      "lastrampok": 1738249982149
    },
    "6285137188171@s.whatsapp.net": {
      "vip": false,
      "badword": 0,
      "title": "",
      "serialNumber": "6bacee468fe796b74e9214930948af06",
      "nick": "🕷🕸",
      "premium": false,
      "totalLimit": 0,
      "limit": 100,
      "uang": 10000,
      "lastclaim": 1738249989170,
      "lastrampok": 1738249989170
    },
    "6281368258661@s.whatsapp.net": {
      "vip": false,
      "badword": 0,
      "title": "",
      "serialNumber": "da5476ccbf7c8f4cd4ad567836090c3f",
      "nick": "Junz Baswedan",
      "premium": false,
      "totalLimit": 0,
      "limit": 100,
      "uang": 10000,
      "lastclaim": 1738250032213,
      "lastrampok": 1738250032213
    },
    "6282326232078@s.whatsapp.net": {
      "vip": false,
      "badword": 0,
      "title": "",
      "serialNumber": "a4d4e76e53b83d7d4a9143a44bfda696",
      "nick": "Mit",
      "premium": false,
      "totalLimit": 0,
      "limit": 100,
      "uang": 10000,
      "lastclaim": 1738250051496,
      "lastrampok": 1738250051496
    },
    "628875417180@s.whatsapp.net": {
      "vip": false,
      "badword": 0,
      "title": "",
      "serialNumber": "ebe5c7f997f7b94f20bebca100703799",
      "nick": "Firman",
      "premium": false,
      "totalLimit": 0,
      "limit": 100,
      "uang": 10000,
      "lastclaim": 1738250073374,
      "lastrampok": 1738250073374
    },
    "6283192652744@s.whatsapp.net": {
      "vip": false,
      "badword": 0,
      "title": "",
      "serialNumber": "a2b439640740df41d445493cdbda0cf1",
      "nick": "adit",
      "premium": false,
      "totalLimit": 0,
      "limit": 100,
      "uang": 10000,
      "lastclaim": 1738250077459,
      "lastrampok": 1738250077459
    },
    "6285757362309@s.whatsapp.net": {
      "vip": false,
      "badword": 0,
      "title": "",
      "serialNumber": "42838f7db0ffa20c99e51d9a90a8ece8",
      "nick": "zil",
      "premium": false,
      "totalLimit": 0,
      "limit": 100,
      "uang": 10000,
      "lastclaim": 1738250081214,
      "lastrampok": 1738250081214
    },
    "62895396770206@s.whatsapp.net": {
      "vip": false,
      "badword": 0,
      "title": "",
      "serialNumber": "ed5139b71d7348db69da0bf2f3b7302b",
      "nick": "ikyikyiky",
      "premium": false,
      "totalLimit": 0,
      "limit": 100,
      "uang": 10000,
      "lastclaim": 1738250114478,
      "lastrampok": 1738250114478
    },
    "6283117005759@s.whatsapp.net": {
      "vip": false,
      "badword": 0,
      "title": "",
      "serialNumber": "55f441d9b512f95d9f29396be254ce4b",
      "nick": "ica",
      "premium": false,
      "totalLimit": 0,
      "limit": 100,
      "uang": 10000,
      "lastclaim": 1738250125704,
      "lastrampok": 1738250125704
    },
    "6285183706254@s.whatsapp.net": {
      "vip": false,
      "badword": 0,
      "title": "",
      "serialNumber": "90c7094e89b4fc7aabbf19d1dd3c7f45",
      "nick": "roky",
      "premium": false,
      "totalLimit": 0,
      "limit": 100,
      "uang": 10000,
      "lastclaim": 1738250141993,
      "lastrampok": 1738250141993
    },
    "6283838427094@s.whatsapp.net": {
      "vip": false,
      "badword": 0,
      "title": "",
      "serialNumber": "5211cc61bfb65f6e7a1bede836f2752b",
      "nick": "ejra",
      "premium": false,
      "totalLimit": 0,
      "limit": 100,
      "uang": 10000,
      "lastclaim": 1738250149066,
      "lastrampok": 1738250149066
    },
    "6288274340259@s.whatsapp.net": {
      "vip": false,
      "badword": 0,
      "title": "",
      "serialNumber": "c61b5a32a5a5b1f4e1616f363d3d8fca",
      "nick": "yaa",
      "premium": false,
      "totalLimit": 0,
      "limit": 100,
      "uang": 10000,
      "lastclaim": 1738250150287,
      "lastrampok": 1738250150287
    },
    "6285772768522@s.whatsapp.net": {
      "vip": false,
      "badword": 0,
      "title": "",
      "serialNumber": "f073af2999691aa9471ca5468e591d28",
      "nick": "celovvip",
      "premium": false,
      "totalLimit": 0,
      "limit": 100,
      "uang": 10000,
      "lastclaim": 1738250155027,
      "lastrampok": 1738250155027
    },
    "6283125797531@s.whatsapp.net": {
      "vip": false,
      "badword": 0,
      "title": "",
      "serialNumber": "4889b7a120d5133651526c113b662f81",
      "nick": "rrrrrrrrr",
      "premium": false,
      "totalLimit": 0,
      "limit": 100,
      "uang": 10000,
      "lastclaim": 1738250183816,
      "lastrampok": 1738250183816
    },
    "6285861178761@s.whatsapp.net": {
      "vip": false,
      "badword": 0,
      "title": "",
      "serialNumber": "24a4519f5394a02857dc599d52c369cb",
      "nick": "ccey ketua mapia",
      "premium": false,
      "totalLimit": 0,
      "limit": 100,
      "uang": 10000,
      "lastclaim": 1738250242047,
      "lastrampok": 1738250242047
    },
    "6289638352991@s.whatsapp.net": {
      "vip": false,
      "badword": 0,
      "title": "",
      "serialNumber": "2c411e81e836a52b16eee884ac982212",
      "nick": "rz",
      "premium": false,
      "totalLimit": 0,
      "limit": 100,
      "uang": 10000,
      "lastclaim": 1738250261904,
      "lastrampok": 1738250261904
    },
    "6282137831424@s.whatsapp.net": {
      "vip": false,
      "badword": 0,
      "title": "",
      "serialNumber": "809f90183052afd2722e95c94664f904",
      "nick": "Ryze",
      "premium": false,
      "totalLimit": 0,
      "limit": 100,
      "uang": 10000,
      "lastclaim": 1738250263879,
      "lastrampok": 1738250263879
    },
    "6283117337737@s.whatsapp.net": {
      "vip": false,
      "badword": 0,
      "title": "",
      "serialNumber": "2a754682d0f0da0e4f378a5d2da30cdd",
      "nick": "HAMZ [7737]",
      "premium": false,
      "totalLimit": 0,
      "limit": 100,
      "uang": 10000,
      "lastclaim": 1738250290900,
      "lastrampok": 1738250290900
    },
    "6281217937383@s.whatsapp.net": {
      "vip": false,
      "badword": 0,
      "title": "",
      "serialNumber": "6113b7bdd164c6712bfca1cd1bdb0c47",
      "nick": "RexxyXD",
      "premium": false,
      "totalLimit": 0,
      "limit": 100,
      "uang": 10000,
      "lastclaim": 1738250293301,
      "lastrampok": 1738250293301
    },
    "6288289625867@s.whatsapp.net": {
      "vip": false,
      "badword": 0,
      "title": "",
      "serialNumber": "e828e3eddf46d4e133b6df070db6af05",
      "nick": "HANZZ",
      "premium": false,
      "totalLimit": 0,
      "limit": 100,
      "uang": 10000,
      "lastclaim": 1738250323664,
      "lastrampok": 1738250323664
    },
    "6283822230457@s.whatsapp.net": {
      "vip": false,
      "badword": 0,
      "title": "",
      "serialNumber": "ba848df25aaa0d686eb306d40c567561",
      "nick": "pinn",
      "premium": false,
      "totalLimit": 0,
      "limit": 100,
      "uang": 10000,
      "lastclaim": 1738250348144,
      "lastrampok": 1738250348144
    }
  },
  "chats": {
    "120363362956531641@g.us": {
      "badword": false,
      "antiforeignnum": false,
      "antiviewonce": false,
      "antibot": false,
      "antispam": false,
      "antimedia": false,
      "antiimage": false,
      "antivideo": false,
      "antiaudio": false,
      "antisticker": false,
      "anticontact": false,
      "antilocation": false,
      "antidocument": false,
      "antilink": false,
      "antilinkgc": true,
      "mute": false
    },
    "120363290964932754@g.us": {
      "badword": false,
      "antiforeignnum": false,
      "antiviewonce": false,
      "antibot": false,
      "antispam": false,
      "antimedia": false,
      "antiimage": false,
      "antivideo": false,
      "antiaudio": false,
      "antisticker": false,
      "anticontact": false,
      "antilocation": false,
      "antidocument": false,
      "antilink": false,
      "antilinkgc": false,
      "mute": false
    },
    "120363322409940857@g.us": {
      "badword": false,
      "antiforeignnum": false,
      "antiviewonce": false,
      "antibot": false,
      "antispam": false,
      "antimedia": false,
      "antiimage": false,
      "antivideo": false,
      "antiaudio": false,
      "antisticker": false,
      "anticontact": false,
      "antilocation": false,
      "antidocument": false,
      "antilink": false,
      "antilinkgc": false,
      "mute": false
    },
    "120363194899675128@g.us": {
      "badword": false,
      "antiforeignnum": false,
      "antiviewonce": false,
      "antibot": false,
      "antispam": false,
      "antimedia": false,
      "antiimage": false,
      "antivideo": false,
      "antiaudio": false,
      "antisticker": false,
      "anticontact": false,
      "antilocation": false,
      "antidocument": false,
      "antilink": false,
      "antilinkgc": false,
      "mute": false
    },
    "6287844551449@s.whatsapp.net": {
      "badword": false,
      "antiforeignnum": false,
      "antiviewonce": false,
      "antibot": false,
      "antispam": false,
      "antimedia": false,
      "antiimage": false,
      "antivideo": false,
      "antiaudio": false,
      "antisticker": false,
      "anticontact": false,
      "antilocation": false,
      "antidocument": false,
      "antilink": false,
      "antilinkgc": false,
      "mute": false
    },
    "120363329057312461@g.us": {
      "badword": false,
      "antiforeignnum": false,
      "antiviewonce": false,
      "antibot": false,
      "antispam": false,
      "antimedia": false,
      "antiimage": false,
      "antivideo": false,
      "antiaudio": false,
      "antisticker": false,
      "anticontact": false,
      "antilocation": false,
      "antidocument": false,
      "antilink": false,
      "antilinkgc": false,
      "mute": false
    },
    "120363312464118948@newsletter": {
      "badword": false,
      "antiforeignnum": false,
      "antiviewonce": false,
      "antibot": false,
      "antispam": false,
      "antimedia": false,
      "antiimage": false,
      "antivideo": false,
      "antiaudio": false,
      "antisticker": false,
      "anticontact": false,
      "antilocation": false,
      "antidocument": false,
      "antilink": false,
      "antilinkgc": false,
      "mute": false
    },
    "120363317025978926@newsletter": {
      "badword": false,
      "antiforeignnum": false,
      "antiviewonce": false,
      "antibot": false,
      "antispam": false,
      "antimedia": false,
      "antiimage": false,
      "antivideo": false,
      "antiaudio": false,
      "antisticker": false,
      "anticontact": false,
      "antilocation": false,
      "antidocument": false,
      "antilink": false,
      "antilinkgc": false,
      "mute": false
    },
    "120363302583491012@newsletter": {
      "badword": false,
      "antiforeignnum": false,
      "antiviewonce": false,
      "antibot": false,
      "antispam": false,
      "antimedia": false,
      "antiimage": false,
      "antivideo": false,
      "antiaudio": false,
      "antisticker": false,
      "anticontact": false,
      "antilocation": false,
      "antidocument": false,
      "antilink": false,
      "antilinkgc": false,
      "mute": false
    },
    "120363039082386818@g.us": {
      "badword": false,
      "antiforeignnum": false,
      "antiviewonce": false,
      "antibot": false,
      "antispam": false,
      "antimedia": false,
      "antiimage": false,
      "antivideo": false,
      "antiaudio": false,
      "antisticker": false,
      "anticontact": false,
      "antilocation": false,
      "antidocument": false,
      "antilink": false,
      "antilinkgc": false,
      "mute": false
    },
    "120363206242850164@g.us": {
      "badword": false,
      "antiforeignnum": false,
      "antiviewonce": false,
      "antibot": false,
      "antispam": false,
      "antimedia": false,
      "antiimage": false,
      "antivideo": false,
      "antiaudio": false,
      "antisticker": false,
      "anticontact": false,
      "antilocation": false,
      "antidocument": false,
      "antilink": false,
      "antilinkgc": false,
      "mute": false
    },
    "120363294372969918@g.us": {
      "badword": false,
      "antiforeignnum": false,
      "antiviewonce": false,
      "antibot": false,
      "antispam": false,
      "antimedia": false,
      "antiimage": false,
      "antivideo": false,
      "antiaudio": false,
      "antisticker": false,
      "anticontact": false,
      "antilocation": false,
      "antidocument": false,
      "antilink": false,
      "antilinkgc": false,
      "mute": false
    },
    "120363344401749353@newsletter": {
      "badword": false,
      "antiforeignnum": false,
      "antiviewonce": false,
      "antibot": false,
      "antispam": false,
      "antimedia": false,
      "antiimage": false,
      "antivideo": false,
      "antiaudio": false,
      "antisticker": false,
      "anticontact": false,
      "antilocation": false,
      "antidocument": false,
      "antilink": false,
      "antilinkgc": false,
      "mute": false
    },
    "6283867042874@s.whatsapp.net": {
      "badword": false,
      "antiforeignnum": false,
      "antiviewonce": false,
      "antibot": false,
      "antispam": false,
      "antimedia": false,
      "antiimage": false,
      "antivideo": false,
      "antiaudio": false,
      "antisticker": false,
      "anticontact": false,
      "antilocation": false,
      "antidocument": false,
      "antilink": false,
      "antilinkgc": false,
      "mute": false
    },
    "120363275187210142@g.us": {
      "badword": false,
      "antiforeignnum": false,
      "antiviewonce": false,
      "antibot": false,
      "antispam": false,
      "antimedia": false,
      "antiimage": false,
      "antivideo": false,
      "antiaudio": false,
      "antisticker": false,
      "anticontact": false,
      "antilocation": false,
      "antidocument": false,
      "antilink": false,
      "antilinkgc": false,
      "mute": false
    },
    "120363323896378788@g.us": {
      "badword": false,
      "antiforeignnum": false,
      "antiviewonce": false,
      "antibot": false,
      "antispam": false,
      "antimedia": false,
      "antiimage": false,
      "antivideo": false,
      "antiaudio": false,
      "antisticker": false,
      "anticontact": false,
      "antilocation": false,
      "antidocument": false,
      "antilink": false,
      "antilinkgc": false,
      "mute": false
    },
    "120363346414594923@newsletter": {
      "badword": false,
      "antiforeignnum": false,
      "antiviewonce": false,
      "antibot": false,
      "antispam": false,
      "antimedia": false,
      "antiimage": false,
      "antivideo": false,
      "antiaudio": false,
      "antisticker": false,
      "anticontact": false,
      "antilocation": false,
      "antidocument": false,
      "antilink": false,
      "antilinkgc": false,
      "mute": false
    },
    "120363272055622034@g.us": {
      "badword": false,
      "antiforeignnum": false,
      "antiviewonce": false,
      "antibot": false,
      "antispam": false,
      "antimedia": false,
      "antiimage": false,
      "antivideo": false,
      "antiaudio": false,
      "antisticker": false,
      "anticontact": false,
      "antilocation": false,
      "antidocument": false,
      "antilink": false,
      "antilinkgc": false,
      "mute": false
    },
    "120363198075123857@newsletter": {
      "badword": false,
      "antiforeignnum": false,
      "antiviewonce": false,
      "antibot": false,
      "antispam": false,
      "antimedia": false,
      "antiimage": false,
      "antivideo": false,
      "antiaudio": false,
      "antisticker": false,
      "anticontact": false,
      "antilocation": false,
      "antidocument": false,
      "antilink": false,
      "antilinkgc": false,
      "mute": false
    },
    "120363372909149226@g.us": {
      "badword": false,
      "antiforeignnum": false,
      "antiviewonce": false,
      "antibot": false,
      "antispam": false,
      "antimedia": false,
      "antiimage": false,
      "antivideo": false,
      "antiaudio": false,
      "antisticker": false,
      "anticontact": false,
      "antilocation": false,
      "antidocument": false,
      "antilink": false,
      "antilinkgc": false,
      "mute": false
    },
    "6289515569752@s.whatsapp.net": {
      "badword": false,
      "antiforeignnum": false,
      "antiviewonce": false,
      "antibot": false,
      "antispam": false,
      "antimedia": false,
      "antiimage": false,
      "antivideo": false,
      "antiaudio": false,
      "antisticker": false,
      "anticontact": false,
      "antilocation": false,
      "antidocument": false,
      "antilink": false,
      "antilinkgc": false,
      "mute": false
    },
    "6285951121822@s.whatsapp.net": {
      "badword": false,
      "antiforeignnum": false,
      "antiviewonce": false,
      "antibot": false,
      "antispam": false,
      "antimedia": false,
      "antiimage": false,
      "antivideo": false,
      "antiaudio": false,
      "antisticker": false,
      "anticontact": false,
      "antilocation": false,
      "antidocument": false,
      "antilink": false,
      "antilinkgc": false,
      "mute": false
    },
    "6285396925719@s.whatsapp.net": {
      "badword": false,
      "antiforeignnum": false,
      "antiviewonce": false,
      "antibot": false,
      "antispam": false,
      "antimedia": false,
      "antiimage": false,
      "antivideo": false,
      "antiaudio": false,
      "antisticker": false,
      "anticontact": false,
      "antilocation": false,
      "antidocument": false,
      "antilink": false,
      "antilinkgc": false,
      "mute": false
    },
    "6283145690217@s.whatsapp.net": {
      "badword": false,
      "antiforeignnum": false,
      "antiviewonce": false,
      "antibot": false,
      "antispam": false,
      "antimedia": false,
      "antiimage": false,
      "antivideo": false,
      "antiaudio": false,
      "antisticker": false,
      "anticontact": false,
      "antilocation": false,
      "antidocument": false,
      "antilink": false,
      "antilinkgc": false,
      "mute": false
    },
    "6283139578685@s.whatsapp.net": {
      "badword": false,
      "antiforeignnum": false,
      "antiviewonce": false,
      "antibot": false,
      "antispam": false,
      "antimedia": false,
      "antiimage": false,
      "antivideo": false,
      "antiaudio": false,
      "antisticker": false,
      "anticontact": false,
      "antilocation": false,
      "antidocument": false,
      "antilink": false,
      "antilinkgc": false,
      "mute": false
    },
    "6283822134057@s.whatsapp.net": {
      "badword": false,
      "antiforeignnum": false,
      "antiviewonce": false,
      "antibot": false,
      "antispam": false,
      "antimedia": false,
      "antiimage": false,
      "antivideo": false,
      "antiaudio": false,
      "antisticker": false,
      "anticontact": false,
      "antilocation": false,
      "antidocument": false,
      "antilink": false,
      "antilinkgc": false,
      "mute": false
    },
    "6289675822211@s.whatsapp.net": {
      "badword": false,
      "antiforeignnum": false,
      "antiviewonce": false,
      "antibot": false,
      "antispam": false,
      "antimedia": false,
      "antiimage": false,
      "antivideo": false,
      "antiaudio": false,
      "antisticker": false,
      "anticontact": false,
      "antilocation": false,
      "antidocument": false,
      "antilink": false,
      "antilinkgc": false,
      "mute": false
    },
    "6285721690014@s.whatsapp.net": {
      "badword": false,
      "antiforeignnum": false,
      "antiviewonce": false,
      "antibot": false,
      "antispam": false,
      "antimedia": false,
      "antiimage": false,
      "antivideo": false,
      "antiaudio": false,
      "antisticker": false,
      "anticontact": false,
      "antilocation": false,
      "antidocument": false,
      "antilink": false,
      "antilinkgc": false,
      "mute": false
    }
  },
  "settings": {
    "6287844551449@s.whatsapp.net": {
      "totalhit": 0,
      "totalError": 0,
      "online": false,
      "safesearch": false,
      "autosticker": false,
      "autodownload": false,
      "autobio": false,
      "autoread": false,
      "autorecordtype": false,
      "autorecord": false,
      "autotype": false,
      "autoblocknum": false,
      "onlygc": false,
      "onlypc": false,
      "watermark": {
        "packname": "Creator",
        "author": "Dcode-al"
      },
      "about": {
        "bot": {
          "nick": "+62 878-4455-1449",
          "alias": "Yaemiko MD"
        },
        "owner": {
          "nick": "+62 838-6704-2874",
          "alias": "6283867042874"
        }
      }
    }
  }
}